{
  "tags" : [ "java", "static" ],
  "answers" : [ {
    "comments" : [ {
      "owner" : {
        "account_id" : 963,
        "reputation" : 18770,
        "user_id" : 37740,
        "user_type" : "registered",
        "accept_rate" : 71,
        "profile_image" : "https://www.gravatar.com/avatar/5e343311e1ed77e61a5faa8ed648e455?s=256&d=identicon&r=PG&f=y&so-version=2",
        "display_name" : "Saj",
        "link" : "https://stackoverflow.com/users/37740/saj"
      },
      "edited" : false,
      "score" : 1,
      "creation_date" : 1226686157,
      "post_id" : 290895,
      "comment_id" : 139389,
      "content_license" : "CC BY-SA 2.5",
      "body" : "&quot;non-static methods belong to instances of the class&quot;  -- The answer. But why it belongs to the instance of the class? Thank you."
    }, {
      "owner" : {
        "account_id" : 5708,
        "reputation" : 61454,
        "user_id" : 9345,
        "user_type" : "registered",
        "accept_rate" : 91,
        "profile_image" : "https://www.gravatar.com/avatar/4c263fe87d408564a9e5f6d1e519aed4?s=256&d=identicon&r=PG",
        "display_name" : "Steven A. Lowe",
        "link" : "https://stackoverflow.com/users/9345/steven-a-lowe"
      },
      "edited" : false,
      "score" : 9,
      "creation_date" : 1226689487,
      "post_id" : 290895,
      "comment_id" : 139508,
      "content_license" : "CC BY-SA 2.5",
      "body" : "@ZiG: because you told it to by not marking it static"
    }, {
      "owner" : {
        "account_id" : 3619295,
        "reputation" : 849,
        "user_id" : 3018474,
        "user_type" : "registered",
        "accept_rate" : 17,
        "profile_image" : "https://i.sstatic.net/VVSMC.jpg?s=256",
        "display_name" : "supritshah1289",
        "link" : "https://stackoverflow.com/users/3018474/supritshah1289"
      },
      "edited" : false,
      "score" : 3,
      "creation_date" : 1513178080,
      "post_id" : 290895,
      "comment_id" : 82553638,
      "content_license" : "CC BY-SA 3.0",
      "body" : "For beginner developers, I have created an example to understand what @StevenA.Lowe mention above. <a href=\"https://repl.it/repls/WavyNeighboringSpotteddolphin\" rel=\"nofollow noreferrer\">repl.it/repls/WavyNeighboringSpotteddolphin</a>"
    } ],
    "owner" : {
      "account_id" : 5708,
      "reputation" : 61454,
      "user_id" : 9345,
      "user_type" : "registered",
      "accept_rate" : 91,
      "profile_image" : "https://www.gravatar.com/avatar/4c263fe87d408564a9e5f6d1e519aed4?s=256&d=identicon&r=PG",
      "display_name" : "Steven A. Lowe",
      "link" : "https://stackoverflow.com/users/9345/steven-a-lowe"
    },
    "is_accepted" : false,
    "score" : 103,
    "last_activity_date" : 1477165616,
    "last_edit_date" : 1477165616,
    "creation_date" : 1226685857,
    "answer_id" : 290895,
    "question_id" : 290884,
    "content_license" : "CC BY-SA 3.0",
    "body" : "<p>The method you are trying to call is an instance-level method; you do not have an instance.</p>\n\n<p><code>static</code> methods belong to the class, non-<code>static</code> methods belong to instances of the class.</p>\n"
  }, {
    "comments" : [ {
      "owner" : {
        "account_id" : 11055,
        "reputation" : 18356,
        "user_id" : 1163802,
        "user_type" : "registered",
        "accept_rate" : 83,
        "profile_image" : "https://i.sstatic.net/1KS0ILe3.jpg?s=256",
        "display_name" : "Vladimir Dyuzhev",
        "link" : "https://stackoverflow.com/users/1163802/vladimir-dyuzhev"
      },
      "edited" : false,
      "score" : 20,
      "creation_date" : 1226692666,
      "post_id" : 290911,
      "comment_id" : 139620,
      "content_license" : "CC BY-SA 2.5",
      "body" : "Method itself does exist. Somewhere in the loaded class definition. So the answer is wrong :)"
    }, {
      "owner" : {
        "account_id" : 8655,
        "reputation" : 21497,
        "user_id" : 15689,
        "user_type" : "registered",
        "accept_rate" : 91,
        "profile_image" : "https://www.gravatar.com/avatar/46bce1bb8135d821c3792456f240e764?s=256&d=identicon&r=PG",
        "display_name" : "Brian Knoblauch",
        "link" : "https://stackoverflow.com/users/15689/brian-knoblauch"
      },
      "edited" : false,
      "score" : 75,
      "creation_date" : 1226694386,
      "post_id" : 290911,
      "comment_id" : 139693,
      "content_license" : "CC BY-SA 2.5",
      "body" : "@Vladimir, OK if you want to be picky. :)  &quot;doesn&#39;t exist in current context&quot; :)"
    }, {
      "owner" : {
        "account_id" : 9324571,
        "reputation" : 1095,
        "user_id" : 6922308,
        "user_type" : "registered",
        "accept_rate" : 55,
        "profile_image" : "https://lh3.googleusercontent.com/-MGxbOFsqaJU/AAAAAAAAAAI/AAAAAAAAAF0/OZf6qM8CUD8/s256-rj/photo.jpg",
        "display_name" : "Anu Shibin Joseph Raj",
        "link" : "https://stackoverflow.com/users/6922308/anu-shibin-joseph-raj"
      },
      "edited" : false,
      "score" : 3,
      "creation_date" : 1484762770,
      "post_id" : 290911,
      "comment_id" : 70647348,
      "content_license" : "CC BY-SA 3.0",
      "body" : "&quot;You can&#39;t call something that doesn&#39;t exist.&quot; - thug :p"
    }, {
      "owner" : {
        "account_id" : 11117292,
        "reputation" : 279,
        "user_id" : 8161256,
        "user_type" : "registered",
        "profile_image" : "https://www.gravatar.com/avatar/4bc768fc1787096f51e32f00dbca455b?s=256&d=identicon&r=PG&f=y&so-version=2",
        "display_name" : "Saathvik",
        "link" : "https://stackoverflow.com/users/8161256/saathvik"
      },
      "edited" : false,
      "score" : 6,
      "creation_date" : 1519282826,
      "post_id" : 290911,
      "comment_id" : 84849005,
      "content_license" : "CC BY-SA 3.0",
      "body" : "A <code>static</code> method cannot tell to which particular object the non-static member belongs to. Since there is no existing object, the non-static method doesn&#39;t belong to any object. Hence there is no way a non-static method can be referenced from <code>static</code> context."
    } ],
    "owner" : {
      "account_id" : 8655,
      "reputation" : 21497,
      "user_id" : 15689,
      "user_type" : "registered",
      "accept_rate" : 91,
      "profile_image" : "https://www.gravatar.com/avatar/46bce1bb8135d821c3792456f240e764?s=256&d=identicon&r=PG",
      "display_name" : "Brian Knoblauch",
      "link" : "https://stackoverflow.com/users/15689/brian-knoblauch"
    },
    "is_accepted" : true,
    "score" : 484,
    "last_activity_date" : 1226686250,
    "creation_date" : 1226686250,
    "answer_id" : 290911,
    "question_id" : 290884,
    "content_license" : "CC BY-SA 2.5",
    "body" : "<p>You can't call something that doesn't exist.  Since you haven't created an object, the non-static method doesn't exist yet.  A static method (by definition) always exists.</p>\n"
  }, {
    "comments" : [ {
      "owner" : {
        "account_id" : 744,
        "reputation" : 4174,
        "user_id" : 972,
        "user_type" : "registered",
        "accept_rate" : 62,
        "profile_image" : "https://i.sstatic.net/7QQCy.jpg?s=256",
        "display_name" : "Hugo",
        "link" : "https://stackoverflow.com/users/972/hugo"
      },
      "edited" : false,
      "score" : 0,
      "creation_date" : 1226734213,
      "post_id" : 290914,
      "comment_id" : 140342,
      "content_license" : "CC BY-SA 2.5",
      "body" : "Not all methods have side-effects! Doesn&#39;t have to be an action <i>to</i>, it could just as well be something that the object tells you."
    } ],
    "owner" : {
      "account_id" : 11385,
      "reputation" : 24312,
      "user_id" : 21925,
      "user_type" : "registered",
      "accept_rate" : 62,
      "profile_image" : "https://www.gravatar.com/avatar/8be4691d697474170946184567d36814?s=256&d=identicon&r=PG",
      "display_name" : "Robin",
      "link" : "https://stackoverflow.com/users/21925/robin"
    },
    "is_accepted" : false,
    "score" : 3,
    "last_activity_date" : 1226686276,
    "creation_date" : 1226686276,
    "answer_id" : 290914,
    "question_id" : 290884,
    "content_license" : "CC BY-SA 2.5",
    "body" : "<p>A static method relates an action to a type of object, whereas the non static method relates an action to an instance of that type of object.  Typically it is a method that does something with relation to the instance.</p>\n\n<p>Ex:</p>\n\n<p>class Car might have a wash method, which would indicate washing a particular car, whereas a static method would apply to the type car.</p>\n"
  }, {
    "owner" : {
      "account_id" : 15446,
      "reputation" : 147018,
      "user_id" : 32632,
      "user_type" : "registered",
      "accept_rate" : 76,
      "profile_image" : "https://www.gravatar.com/avatar/bbf4bacbdb15894cbf7f59718e3fc5cf?s=256&d=identicon&r=PG",
      "display_name" : "Charles Bretana",
      "link" : "https://stackoverflow.com/users/32632/charles-bretana"
    },
    "is_accepted" : false,
    "score" : 3,
    "last_activity_date" : 1226686310,
    "creation_date" : 1226686310,
    "answer_id" : 290917,
    "question_id" : 290884,
    "content_license" : "CC BY-SA 2.5",
    "body" : "<p>if a method is not static, that \"tells\" the compiler that the method requires access to instance-level data in the class, (like a non-static field).  This data would not be available unless an instance of the class has been created.  So the compiler throws an error if you try to call the method from a static method.. If in fact the method does NOT reference any non-static member of the class, make the method static.</p>\n\n<p>In Resharper, for example, just creating a non-static method that does NOT reference any static member of the class generates a warning message \"This method can be made static\" </p>\n"
  }, {
    "owner" : {
      "account_id" : 3370,
      "reputation" : 7202,
      "user_id" : 4857,
      "user_type" : "registered",
      "accept_rate" : 96,
      "profile_image" : "https://i.sstatic.net/cxMVR.jpg?s=256",
      "display_name" : "Ande Turner",
      "link" : "https://stackoverflow.com/users/4857/ande-turner"
    },
    "is_accepted" : false,
    "community_owned_date" : 1226734288,
    "score" : 9,
    "last_activity_date" : 1239112090,
    "last_edit_date" : 1239112090,
    "creation_date" : 1226733521,
    "answer_id" : 292263,
    "question_id" : 290884,
    "content_license" : "CC BY-SA 2.5",
    "body" : "<p>The answers so far describe why, but here is a something else you might want to consider: </p>\n\n<p>You can can call a method from an instantiable class by appending a method call to its constructor, </p>\n\n<pre><code>Object instance = new Constuctor().methodCall();\n</code></pre>\n\n<p>or</p>\n\n<pre><code>primitive name = new Constuctor().methodCall();\n</code></pre>\n\n<p>This is useful it you only wish to use a method of an instantiable class once within a single scope.  If you are calling multiple methods from an instantiable class within a single scope, definitely create a referable instance.</p>\n"
  }, {
    "comments" : [ {
      "owner" : {
        "account_id" : 2812953,
        "reputation" : 3172,
        "user_id" : 2418793,
        "user_type" : "registered",
        "accept_rate" : 62,
        "profile_image" : "https://i.sstatic.net/nQ6dp.jpg?s=256",
        "display_name" : "Azurespot",
        "link" : "https://stackoverflow.com/users/2418793/azurespot"
      },
      "edited" : false,
      "score" : 0,
      "creation_date" : 1399273101,
      "post_id" : 292271,
      "comment_id" : 35976690,
      "content_license" : "CC BY-SA 3.0",
      "body" : "I have encountered this problem with the error mentioned above, but must learn how to use static in order to use an instance of a class across different activities, so I am stuck struggling with it. :( trying so many things, but not working."
    } ],
    "owner" : {
      "account_id" : 744,
      "reputation" : 4174,
      "user_id" : 972,
      "user_type" : "registered",
      "accept_rate" : 62,
      "profile_image" : "https://i.sstatic.net/7QQCy.jpg?s=256",
      "display_name" : "Hugo",
      "link" : "https://stackoverflow.com/users/972/hugo"
    },
    "is_accepted" : false,
    "score" : 16,
    "last_activity_date" : 1226734116,
    "creation_date" : 1226734116,
    "answer_id" : 292271,
    "question_id" : 290884,
    "content_license" : "CC BY-SA 2.5",
    "body" : "<p>I just realized, I think people shouldn't be exposed to the concept of \"static\" very early.</p>\n\n<p>Static methods should probably be the exception rather than the norm. Especially early on anyways if you want to learn OOP. (Why start with an exception to the rule?) That's very counter-pedagogical of Java, that the \"first\" thing you should learn is the public <em>static</em> void main thing. (Few real Java applications have their own main methods anyways.)</p>\n"
  }, {
    "owner" : {
      "user_type" : "does_not_exist",
      "display_name" : "antiparagon"
    },
    "is_accepted" : false,
    "score" : 3,
    "last_activity_date" : 1239194398,
    "last_edit_date" : 1239194398,
    "creation_date" : 1239113364,
    "answer_id" : 725928,
    "question_id" : 290884,
    "content_license" : "CC BY-SA 2.5",
    "body" : "<p>The compiler actually adds an argument to non-static methods. It adds a <code>this pointer/reference. This is also the reason why a static method can not use this</code>, because there is no object.</p>\n"
  }, {
    "comments" : [ {
      "owner" : {
        "account_id" : 170035,
        "reputation" : 6682,
        "user_id" : 396483,
        "user_type" : "registered",
        "accept_rate" : 68,
        "profile_image" : "https://i.sstatic.net/H9TkA.jpg?s=256",
        "display_name" : "john k",
        "link" : "https://stackoverflow.com/users/396483/john-k"
      },
      "edited" : false,
      "score" : 0,
      "creation_date" : 1669127119,
      "post_id" : 1140431,
      "comment_id" : 131569770,
      "content_license" : "CC BY-SA 4.0",
      "body" : "&quot;It&#39;s a language design decision&quot;  This."
    }, {
      "owner" : {
        "account_id" : 11430844,
        "reputation" : 61,
        "user_id" : 8379594,
        "user_type" : "registered",
        "profile_image" : "https://www.gravatar.com/avatar/31396d1777a23c75df84c0ae1f7fb4f9?s=256&d=identicon&r=PG&f=y&so-version=2",
        "display_name" : "ss123",
        "link" : "https://stackoverflow.com/users/8379594/ss123"
      },
      "edited" : false,
      "score" : 0,
      "creation_date" : 1712908887,
      "post_id" : 1140431,
      "comment_id" : 138067198,
      "content_license" : "CC BY-SA 4.0",
      "body" : "I just tried to call an instance method using no instance variables from the main(). I still got the error complaining <i>non-static method binSearch() cannot be referenced from a static context</i>      void binSearch() {          System.out.println(&quot;I use no instance variables&quot;);     }"
    }, {
      "owner" : {
        "account_id" : 9193,
        "reputation" : 347252,
        "user_id" : 16883,
        "user_type" : "registered",
        "accept_rate" : 83,
        "profile_image" : "https://www.gravatar.com/avatar/0382297f273df0a544b0c6c2734de096?s=256&d=identicon&r=PG",
        "display_name" : "Michael Borgwardt",
        "link" : "https://stackoverflow.com/users/16883/michael-borgwardt"
      },
      "edited" : false,
      "score" : 0,
      "creation_date" : 1712911040,
      "post_id" : 1140431,
      "comment_id" : 138067517,
      "content_license" : "CC BY-SA 4.0",
      "body" : "Right, my last sentence was worded wrong, I&#39;ll fix it. It&#39;s not allowed because it&#39;s still conceptually wrong, even if technically the code could execute in a static context. Either make it a static method, or call it through an instance."
    } ],
    "owner" : {
      "account_id" : 9193,
      "reputation" : 347252,
      "user_id" : 16883,
      "user_type" : "registered",
      "accept_rate" : 83,
      "profile_image" : "https://www.gravatar.com/avatar/0382297f273df0a544b0c6c2734de096?s=256&d=identicon&r=PG",
      "display_name" : "Michael Borgwardt",
      "link" : "https://stackoverflow.com/users/16883/michael-borgwardt"
    },
    "is_accepted" : false,
    "score" : 32,
    "last_activity_date" : 1712911077,
    "last_edit_date" : 1712911077,
    "creation_date" : 1247779810,
    "answer_id" : 1140431,
    "question_id" : 290884,
    "content_license" : "CC BY-SA 4.0",
    "body" : "<p>The essence of object oriented programming is encapsulating logic together with the data it operates on.</p>\n<p>Instance methods are the logic, instance fields are the data. Together, they form an object.</p>\n<pre><code>public class Foo\n{\n    private String foo;\n    public Foo(String foo){ this.foo = foo; }\n    public getFoo(){ return this.foo; }\n\n    public static void main(String[] args){\n        System.out.println( getFoo() );\n    }\n}\n</code></pre>\n<p>What could possibly be the result of running the above program?</p>\n<p>Without an object, there is no instance data, and while the instance methods exist as part of the class definition, they need an object instance to provide data for them.</p>\n<p>In theory, an instance method that does not access any instance data could work in a static context, but then there isn't really any reason for it to be an instance method. It's a language design decision to forbid it anyway rather than making up an extra rule to allow it.</p>\n"
  }, {
    "owner" : {
      "account_id" : 778075,
      "reputation" : 19,
      "user_id" : 829891,
      "user_type" : "unregistered",
      "profile_image" : "https://www.gravatar.com/avatar/47b568c79055de27cef22b73dd5b1665?s=256&d=identicon&r=PG",
      "display_name" : "Vipul",
      "link" : "https://stackoverflow.com/users/829891/vipul"
    },
    "is_accepted" : false,
    "score" : 1,
    "last_activity_date" : 1389208231,
    "last_edit_date" : 1389208231,
    "creation_date" : 1309875785,
    "answer_id" : 6584225,
    "question_id" : 290884,
    "content_license" : "CC BY-SA 3.0",
    "body" : "<p>The simple reason behind this is that Static data members of parent class\ncan be accessed (only if they are not overridden) but for instance(non-static)\ndata members or methods we need their reference and so they can only be\ncalled through an object.</p>\n"
  }, {
    "owner" : {
      "account_id" : 216101,
      "reputation" : 27465,
      "user_id" : 471129,
      "user_type" : "registered",
      "profile_image" : "https://i.sstatic.net/CS444.jpg?s=256",
      "display_name" : "Erik Eidt",
      "link" : "https://stackoverflow.com/users/471129/erik-eidt"
    },
    "is_accepted" : false,
    "score" : 16,
    "last_activity_date" : 1516815743,
    "last_edit_date" : 1516815743,
    "creation_date" : 1342380031,
    "answer_id" : 11494870,
    "question_id" : 290884,
    "content_license" : "CC BY-SA 3.0",
    "body" : "<p>I think it is worth pointing out that by the rules of the Java language the Java compiler inserts the equivalent of \"this.\" when it notices that you're accessing instance methods or instance fields without an explicit instance.  Of course, the compiler knows that it can only do this from within an instance method, which has a \"this\" variable, as static methods don't.</p>\n\n<p>Which means that when you're in an instance method the following are equivalent:</p>\n\n<pre><code>instanceMethod();\nthis.instanceMethod();\n</code></pre>\n\n<p>and these are also equivalent:</p>\n\n<pre><code>... = instanceField;\n... = this.instanceField;\n</code></pre>\n\n<p>The compiler is effectively inserting the \"this.\" when you don't supply a specific instance.  </p>\n\n<p>This (pun intended) bit of \"magic help\" by the compiler can confuse novices: it means that instance calls and static calls sometimes appear to have the same syntax while in reality are calls of different types and underlying mechanisms.</p>\n\n<p>The instance method call is sometimes referred to as a method invocation or dispatch because of the behaviors of virtual methods supporting polymorphism; dispatching behavior happens regardless of whether you wrote an explicit object instance to use or the compiler inserted a \"this.\".</p>\n\n<p>The static method call mechanism is simpler, like a function call in a non-OOP language.</p>\n\n<p>Personally, I think the error message is misleading, it could read \"non-static method cannot be referenced from a static context <em>without specifying an explicit object instance</em>\".  </p>\n\n<hr>\n\n<p>What the compiler is complaining about is that it cannot simply insert the standard \"this.\" as it does within instance methods, because this code is within a static method; however, maybe the author merely forgot to supply the instance of interest for this invocation &#8212; say, an instance possibly supplied to the static method as parameter, or created within this static method.  </p>\n\n<p>In short, you most certainly can call instance methods from within a static method, you just need to have and specify an explicit instance object for the invocation.</p>\n"
  }, {
    "owner" : {
      "account_id" : 3317025,
      "reputation" : 2032,
      "user_id" : 2789764,
      "user_type" : "registered",
      "accept_rate" : 92,
      "profile_image" : "https://graph.facebook.com/832045402/picture?type=large",
      "display_name" : "Vivek Vermani",
      "link" : "https://stackoverflow.com/users/2789764/vivek-vermani"
    },
    "is_accepted" : false,
    "score" : 5,
    "last_activity_date" : 1457299219,
    "last_edit_date" : 1457299219,
    "creation_date" : 1402001179,
    "answer_id" : 24069960,
    "question_id" : 290884,
    "content_license" : "CC BY-SA 3.0",
    "body" : "<p>If we try to access an instance method from a static context , the compiler has no way to guess which instance method ( variable for which object ), you are referring to. Though, you can always access it using an object reference.</p>\n"
  }, {
    "comments" : [ {
      "owner" : {
        "account_id" : 170035,
        "reputation" : 6682,
        "user_id" : 396483,
        "user_type" : "registered",
        "accept_rate" : 68,
        "profile_image" : "https://i.sstatic.net/H9TkA.jpg?s=256",
        "display_name" : "john k",
        "link" : "https://stackoverflow.com/users/396483/john-k"
      },
      "edited" : false,
      "score" : 0,
      "creation_date" : 1669127075,
      "post_id" : 25414977,
      "comment_id" : 131569747,
      "content_license" : "CC BY-SA 4.0",
      "body" : "yeah, but the very fact you execute the main() class proves that there is memory allocated and the operating system is reading and writing your code."
    } ],
    "owner" : {
      "account_id" : 4790565,
      "reputation" : 21,
      "user_id" : 3869877,
      "user_type" : "registered",
      "profile_image" : "https://www.gravatar.com/avatar/ebc47d579cf61dd0621fdbb74640e9b2?s=256&d=identicon&r=PG&f=y&so-version=2",
      "display_name" : "Cristi&#225;n Munizaga",
      "link" : "https://stackoverflow.com/users/3869877/cristi%c3%a1n-munizaga"
    },
    "is_accepted" : false,
    "score" : 2,
    "last_activity_date" : 1408571304,
    "creation_date" : 1408571304,
    "answer_id" : 25414977,
    "question_id" : 290884,
    "content_license" : "CC BY-SA 3.0",
    "body" : "<p>So you are asking for a very core reason? </p>\n\n<p>Well, since you are developing in Java, the compiler generates an object code that the Java Virtual Machine can interpret. The JVM anyway is a binary program that run in machine language (probably the JVM’s version specific for your operating system and hardware was previously compiled by another programming language like C in order to get a machine code that can run in your processor). At the end, any code is translated to machine code. So, create an object (an instance of a class) is equivalent to reserve a memory space (memory registers that will be processor registers when the CPU scheduler of the operating system put your program at the top of the queue in order to execute it) to have a data storage place that can be able to read and write data. If you don’t have an instance of a class (which happens on a static context), then you don’t have that memory space to read or write the data. In fact, like other people had said, the data don’t exist (because from the begin you never had written neither had reserved the memory space to store it).</p>\n\n<p>Sorry for my english! I'm latin!</p>\n"
  }, {
    "owner" : {
      "account_id" : 4308181,
      "reputation" : 123,
      "user_id" : 3520028,
      "user_type" : "registered",
      "profile_image" : "https://www.gravatar.com/avatar/3110ed7f79a7c3db45718f6fcc27da3f?s=256&d=identicon&r=PG&f=y&so-version=2",
      "display_name" : "Ejesalva",
      "link" : "https://stackoverflow.com/users/3520028/ejesalva"
    },
    "is_accepted" : false,
    "score" : 1,
    "last_activity_date" : 1410621007,
    "creation_date" : 1410621007,
    "answer_id" : 25824497,
    "question_id" : 290884,
    "content_license" : "CC BY-SA 3.0",
    "body" : "<p>A non-static method is dependent on the object. It is recognized by the program once the object is created.  </p>\n\n<p>Static methods can be called even before the creation of an object. Static methods are great for doing comparisons or operations that aren't dependent on the actual objects you plan to work with.</p>\n"
  } ],
  "owner" : {
    "account_id" : 963,
    "reputation" : 18770,
    "user_id" : 37740,
    "user_type" : "registered",
    "accept_rate" : 71,
    "profile_image" : "https://www.gravatar.com/avatar/5e343311e1ed77e61a5faa8ed648e455?s=256&d=identicon&r=PG&f=y&so-version=2",
    "display_name" : "Saj",
    "link" : "https://stackoverflow.com/users/37740/saj"
  },
  "is_answered" : true,
  "view_count" : 1210130,
  "closed_date" : 1420981557,
  "accepted_answer_id" : 290911,
  "answer_count" : 13,
  "score" : 389,
  "last_activity_date" : 1712911077,
  "creation_date" : 1226685570,
  "last_edit_date" : 1627364190,
  "question_id" : 290884,
  "link" : "https://stackoverflow.com/questions/290884/what-is-the-reason-behind-non-static-method-cannot-be-referenced-from-a-static",
  "closed_reason" : "Duplicate",
  "title" : "What is the reason behind &quot;non-static method cannot be referenced from a static context&quot;?",
  "body" : "<p>The very common beginner mistake is when you try to use a class property &quot;statically&quot; without making an instance of that class. It leaves you with the mentioned error message:</p>\n<blockquote>\n<p>You can either make the non static method static or make an instance of that class to use its properties.</p>\n</blockquote>\n<p><strong>What the reason behind this? Am not concern with the solution, rather the reason.</strong></p>\n<pre><code>private java.util.List&lt;String&gt; someMethod(){\n    /* Some Code */\n    return someList;            \n}\n\npublic static void main(String[] strArgs){          \n     // The following statement causes the error. \n    java.util.List&lt;String&gt; someList = someMethod();         \n}\n</code></pre>\n"
}