{
  "tags" : [ "java", "apache-httpclient-4.x", "apache-commons" ],
  "comments" : [ {
    "owner" : {
      "account_id" : 151394,
      "reputation" : 53743,
      "user_id" : 365237,
      "user_type" : "registered",
      "accept_rate" : 96,
      "profile_image" : "https://www.gravatar.com/avatar/fb9385b7f1a792d5159eca8bbb2c34f8?s=256&d=identicon&r=PG",
      "display_name" : "eis",
      "link" : "https://stackoverflow.com/users/365237/eis"
    },
    "edited" : false,
    "score" : 1,
    "creation_date" : 1466522374,
    "post_id" : 5769717,
    "comment_id" : 63345601,
    "content_license" : "CC BY-SA 3.0",
    "body" : "Since the question and all the answers seem to be about apache libraries, this should be tagged as such. I don&#39;t see anything without using 3rdparty libs."
  }, {
    "owner" : {
      "account_id" : 2078462,
      "reputation" : 10752,
      "user_id" : 2986984,
      "user_type" : "registered",
      "accept_rate" : 80,
      "profile_image" : "https://www.gravatar.com/avatar/45f2bc89b6610a463cde6865848a193d?s=256&d=identicon&r=PG",
      "display_name" : "tkruse",
      "link" : "https://stackoverflow.com/users/2986984/tkruse"
    },
    "edited" : false,
    "score" : 0,
    "creation_date" : 1584066541,
    "post_id" : 5769717,
    "comment_id" : 107329287,
    "content_license" : "CC BY-SA 4.0",
    "body" : "related: <a href=\"https://stackoverflow.com/questions/21574478\">stackoverflow.com/questions/21574478</a>"
  } ],
  "answers" : [ {
    "comments" : [ {
      "owner" : {
        "account_id" : 246,
        "reputation" : 109219,
        "user_id" : 304,
        "user_type" : "registered",
        "accept_rate" : 40,
        "profile_image" : "https://www.gravatar.com/avatar/9061706d2661cf0fa9f2df0eee56cf9b?s=256&d=identicon&r=PG",
        "display_name" : "McDowell",
        "link" : "https://stackoverflow.com/users/304/mcdowell"
      },
      "reply_to_user" : {
        "account_id" : 329612,
        "reputation" : 72239,
        "user_id" : 653230,
        "user_type" : "registered",
        "profile_image" : "https://www.gravatar.com/avatar/8adc8afef3a25bf45a31686f786149d0?s=256&d=identicon&r=PG",
        "display_name" : "WhiteFang34",
        "link" : "https://stackoverflow.com/users/653230/whitefang34"
      },
      "edited" : false,
      "score" : 4,
      "creation_date" : 1303640423,
      "post_id" : 5769756,
      "comment_id" : 6609544,
      "content_license" : "CC BY-SA 3.0",
      "body" : "this will corrupt text in many cases as the method uses the system default text encoding which varies based on OS and user settings."
    }, {
      "owner" : {
        "account_id" : 329612,
        "reputation" : 72239,
        "user_id" : 653230,
        "user_type" : "registered",
        "profile_image" : "https://www.gravatar.com/avatar/8adc8afef3a25bf45a31686f786149d0?s=256&d=identicon&r=PG",
        "display_name" : "WhiteFang34",
        "link" : "https://stackoverflow.com/users/653230/whitefang34"
      },
      "reply_to_user" : {
        "account_id" : 246,
        "reputation" : 109219,
        "user_id" : 304,
        "user_type" : "registered",
        "accept_rate" : 40,
        "profile_image" : "https://www.gravatar.com/avatar/9061706d2661cf0fa9f2df0eee56cf9b?s=256&d=identicon&r=PG",
        "display_name" : "McDowell",
        "link" : "https://stackoverflow.com/users/304/mcdowell"
      },
      "edited" : false,
      "score" : 1,
      "creation_date" : 1303641011,
      "post_id" : 5769756,
      "comment_id" : 6609599,
      "content_license" : "CC BY-SA 3.0",
      "body" : "@McDowell: oops thanks, I linked the javadoc for the method with encoding but I forgot to use it in the example. I added UTF-8 to the example for now, although technically should use the <code>Content-Encoding</code> header from the response if available."
    }, {
      "owner" : {
        "account_id" : 210105,
        "reputation" : 685,
        "user_id" : 461529,
        "user_type" : "registered",
        "profile_image" : "https://www.gravatar.com/avatar/1de77c99ff2b7384a42fcede3ce45e75?s=256&d=identicon&r=PG",
        "display_name" : "Timur Yusupov",
        "link" : "https://stackoverflow.com/users/461529/timur-yusupov"
      },
      "edited" : false,
      "score" : 8,
      "creation_date" : 1328624265,
      "post_id" : 5769756,
      "comment_id" : 11546192,
      "content_license" : "CC BY-SA 3.0",
      "body" : "Actually charset is specified in contentType like &quot;charset=...&quot;, but not in contentEncoding, which contains something like &#39;gzip&#39;"
    }, {
      "owner" : {
        "user_type" : "does_not_exist",
        "display_name" : "user168237"
      },
      "edited" : false,
      "score" : 0,
      "creation_date" : 1366165559,
      "post_id" : 5769756,
      "comment_id" : 22903371,
      "content_license" : "CC BY-SA 3.0",
      "body" : "Do I have to close the InputStream?"
    }, {
      "owner" : {
        "account_id" : 400295,
        "reputation" : 724,
        "user_id" : 766200,
        "user_type" : "registered",
        "accept_rate" : 56,
        "profile_image" : "https://www.gravatar.com/avatar/50e08fbf4a941b9cb05dd8da3e837ca0?s=256&d=identicon&r=PG",
        "display_name" : "amIT",
        "link" : "https://stackoverflow.com/users/766200/amit"
      },
      "edited" : false,
      "score" : 1,
      "creation_date" : 1426245946,
      "post_id" : 5769756,
      "comment_id" : 46302968,
      "content_license" : "CC BY-SA 3.0",
      "body" : "this   function causes  the input stream  to  be closed, is there a  way @WhiteFang34 i  can print  my  response   and  continue  to  use the http  entity"
    }, {
      "owner" : {
        "account_id" : 3567308,
        "reputation" : 1030,
        "user_id" : 2978502,
        "user_type" : "registered",
        "profile_image" : "https://i.sstatic.net/tBVdI.jpg?s=256",
        "display_name" : "dhanyn10",
        "link" : "https://stackoverflow.com/users/2978502/dhanyn10"
      },
      "edited" : false,
      "score" : 0,
      "creation_date" : 1674316311,
      "post_id" : 5769756,
      "comment_id" : 132690696,
      "content_license" : "CC BY-SA 4.0",
      "body" : "this is link for apache commons <a href=\"https://mvnrepository.com/artifact/commons-io/commons-io/2.11.0\" rel=\"nofollow noreferrer\">mvnrepository.com/artifact/commons-io/commons-io/2.11.0</a>"
    } ],
    "owner" : {
      "account_id" : 329612,
      "reputation" : 72239,
      "user_id" : 653230,
      "user_type" : "registered",
      "profile_image" : "https://www.gravatar.com/avatar/8adc8afef3a25bf45a31686f786149d0?s=256&d=identicon&r=PG",
      "display_name" : "WhiteFang34",
      "link" : "https://stackoverflow.com/users/653230/whitefang34"
    },
    "is_accepted" : true,
    "score" : 120,
    "last_activity_date" : 1303641396,
    "last_edit_date" : 1303641396,
    "creation_date" : 1303637629,
    "answer_id" : 5769756,
    "question_id" : 5769717,
    "content_license" : "CC BY-SA 3.0",
    "body" : "<p>Every library I can think of returns a stream. You could use <a href=\"http://commons.apache.org/io/apidocs/org/apache/commons/io/IOUtils.html#toString%28java.io.InputStream,%20java.lang.String%29\" rel=\"noreferrer\"><code>IOUtils.toString()</code></a> from <a href=\"http://commons.apache.org/io/\" rel=\"noreferrer\">Apache Commons IO</a> to read an <code>InputStream</code> into a <code>String</code> in one method call. E.g.:</p>\n\n<pre><code>URL url = new URL(\"http://www.example.com/\");\nURLConnection con = url.openConnection();\nInputStream in = con.getInputStream();\nString encoding = con.getContentEncoding();\nencoding = encoding == null ? \"UTF-8\" : encoding;\nString body = IOUtils.toString(in, encoding);\nSystem.out.println(body);\n</code></pre>\n\n<p><strong>Update:</strong> I changed the example above to use the content encoding from the response if available. Otherwise it'll default to UTF-8 as a best guess, instead of using the local system default.</p>\n"
  }, {
    "comments" : [ {
      "owner" : {
        "account_id" : 1925311,
        "reputation" : 1399,
        "user_id" : 1735921,
        "user_type" : "registered",
        "accept_rate" : 85,
        "profile_image" : "https://i.sstatic.net/3xEka.jpg?s=256",
        "display_name" : "user1735921",
        "link" : "https://stackoverflow.com/users/1735921/user1735921"
      },
      "edited" : false,
      "score" : 0,
      "creation_date" : 1542789464,
      "post_id" : 5769991,
      "comment_id" : 93690868,
      "content_license" : "CC BY-SA 4.0",
      "body" : "how to get it as HashMap ? I get response as Json, how to read that?"
    } ],
    "owner" : {
      "account_id" : 246,
      "reputation" : 109219,
      "user_id" : 304,
      "user_type" : "registered",
      "accept_rate" : 40,
      "profile_image" : "https://www.gravatar.com/avatar/9061706d2661cf0fa9f2df0eee56cf9b?s=256&d=identicon&r=PG",
      "display_name" : "McDowell",
      "link" : "https://stackoverflow.com/users/304/mcdowell"
    },
    "is_accepted" : false,
    "score" : 30,
    "last_activity_date" : 1303640287,
    "creation_date" : 1303640287,
    "answer_id" : 5769991,
    "question_id" : 5769717,
    "content_license" : "CC BY-SA 3.0",
    "body" : "<p>This is relatively simple in the specific case, but quite tricky in the general case.</p>\n\n<pre><code>HttpClient httpclient = new DefaultHttpClient();\nHttpGet httpget = new HttpGet(\"http://stackoverflow.com/\");\nHttpResponse response = httpclient.execute(httpget);\nHttpEntity entity = response.getEntity();\nSystem.out.println(EntityUtils.getContentMimeType(entity));\nSystem.out.println(EntityUtils.getContentCharSet(entity));\n</code></pre>\n\n<p>The answer depends on the <code>Content-Type</code> <a href=\"http://en.wikipedia.org/wiki/HTTP_header#Responses\" rel=\"noreferrer\">HTTP response header</a>.</p>\n\n<p>This header contains information about the payload and <em>might</em> define the encoding of textual data. Even if you assume <a href=\"http://en.wikipedia.org/wiki/Internet_media_type#Type_text\" rel=\"noreferrer\">text types</a>, you may need to inspect the content itself in order to determine the correct character encoding. <em>E.g. see the <a href=\"http://www.w3.org/TR/html4/charset.html#h-5.2.2\" rel=\"noreferrer\">HTML 4 spec</a> for details on how to do that for that particular format.</em></p>\n\n<p>Once the encoding is known, an <a href=\"http://download.oracle.com/javase/6/docs/api/java/io/InputStreamReader.html#InputStreamReader%28java.io.InputStream,%20java.nio.charset.Charset%29\" rel=\"noreferrer\">InputStreamReader</a> can be used to decode the data.</p>\n\n<p><em>This answer depends on the server doing the right thing - if you want to handle cases where the response headers don't match the document, or the document declarations don't match the encoding used, that's another kettle of fish.</em></p>\n"
  }, {
    "owner" : {
      "account_id" : 130610,
      "reputation" : 10650,
      "user_id" : 329993,
      "user_type" : "registered",
      "accept_rate" : 84,
      "profile_image" : "https://i.sstatic.net/a3sch.jpg?s=256",
      "display_name" : "moonlightcheese",
      "link" : "https://stackoverflow.com/users/329993/moonlightcheese"
    },
    "is_accepted" : false,
    "score" : 55,
    "last_activity_date" : 1331069847,
    "creation_date" : 1331069847,
    "answer_id" : 9592318,
    "question_id" : 5769717,
    "content_license" : "CC BY-SA 3.0",
    "body" : "<p>Here's an example from another simple project I was working on using the httpclient library from Apache:</p>\n\n<pre><code>String response = new String();\nList&lt;NameValuePair&gt; nameValuePairs = new ArrayList&lt;NameValuePair&gt;(1);\nnameValuePairs.add(new BasicNameValuePair(\"j\", request));\nHttpEntity requestEntity = new UrlEncodedFormEntity(nameValuePairs);\n\nHttpPost httpPost = new HttpPost(mURI);\nhttpPost.setEntity(requestEntity);\nHttpResponse httpResponse = mHttpClient.execute(httpPost);\nHttpEntity responseEntity = httpResponse.getEntity();\nif(responseEntity!=null) {\n    response = EntityUtils.toString(responseEntity);\n}\n</code></pre>\n\n<p>just use EntityUtils to grab the response body as a String.  very simple.</p>\n"
  }, {
    "owner" : {
      "account_id" : 1006204,
      "reputation" : 2581,
      "user_id" : 1019922,
      "user_type" : "registered",
      "profile_image" : "https://www.gravatar.com/avatar/d17fbc7cda170ae81e1f00d083a4100e?s=256&d=identicon&r=PG",
      "display_name" : "Eric Schlenz",
      "link" : "https://stackoverflow.com/users/1019922/eric-schlenz"
    },
    "is_accepted" : false,
    "score" : 9,
    "last_activity_date" : 1341008517,
    "last_edit_date" : 1341008517,
    "creation_date" : 1332428293,
    "answer_id" : 9824843,
    "question_id" : 5769717,
    "content_license" : "CC BY-SA 3.0",
    "body" : "<p>How about just this?</p>\n\n<pre><code>org.apache.commons.io.IOUtils.toString(new URL(\"http://www.someurl.com/\"));\n</code></pre>\n"
  }, {
    "comments" : [ {
      "owner" : {
        "account_id" : 1108280,
        "reputation" : 872,
        "user_id" : 1099211,
        "user_type" : "registered",
        "accept_rate" : 90,
        "profile_image" : "https://www.gravatar.com/avatar/69b117784e6c2f8543a5be2777a50b97?s=256&d=identicon&r=PG",
        "display_name" : "Tirtha",
        "link" : "https://stackoverflow.com/users/1099211/tirtha"
      },
      "edited" : false,
      "score" : 14,
      "creation_date" : 1374648167,
      "post_id" : 13742322,
      "comment_id" : 26017367,
      "content_license" : "CC BY-SA 3.0",
      "body" : "The only problem I faced with method 1 is, the entity object is consumed when you do <code>response.getEntity()</code> and it is now available as <code>responseString</code>. if you try to do a response.getEntity() again, it&#39;ll return <code>IllegalStateException</code>."
    }, {
      "owner" : {
        "account_id" : 482314,
        "reputation" : 430,
        "user_id" : 896650,
        "user_type" : "registered",
        "accept_rate" : 57,
        "profile_image" : "https://www.gravatar.com/avatar/e6f1043de11745a009bf6b281ae4e527?s=256&d=identicon&r=PG",
        "display_name" : "Jaroslav Štreit",
        "link" : "https://stackoverflow.com/users/896650/jaroslav-%c5%a0treit"
      },
      "edited" : false,
      "score" : 0,
      "creation_date" : 1476701635,
      "post_id" : 13742322,
      "comment_id" : 67441494,
      "content_license" : "CC BY-SA 3.0",
      "body" : "Worked in my case - getting body from CloseableHttpClient response."
    }, {
      "owner" : {
        "account_id" : 3048674,
        "reputation" : 2981,
        "user_id" : 2583733,
        "user_type" : "registered",
        "accept_rate" : 50,
        "profile_image" : "https://i.sstatic.net/dJhPY.jpg?s=256",
        "display_name" : "Andreas L.",
        "link" : "https://stackoverflow.com/users/2583733/andreas-l"
      },
      "edited" : false,
      "score" : 2,
      "creation_date" : 1499168913,
      "post_id" : 13742322,
      "comment_id" : 76787210,
      "content_license" : "CC BY-SA 3.0",
      "body" : "What is httpClient?!"
    }, {
      "owner" : {
        "account_id" : 2118276,
        "reputation" : 3644,
        "user_id" : 1882094,
        "user_type" : "registered",
        "profile_image" : "https://www.gravatar.com/avatar/ed08f34076746a286a31b1e3a8cbfe6a?s=256&d=identicon&r=PG",
        "display_name" : "spideringweb",
        "link" : "https://stackoverflow.com/users/1882094/spideringweb"
      },
      "reply_to_user" : {
        "account_id" : 3048674,
        "reputation" : 2981,
        "user_id" : 2583733,
        "user_type" : "registered",
        "accept_rate" : 50,
        "profile_image" : "https://i.sstatic.net/dJhPY.jpg?s=256",
        "display_name" : "Andreas L.",
        "link" : "https://stackoverflow.com/users/2583733/andreas-l"
      },
      "edited" : false,
      "score" : 1,
      "creation_date" : 1499974734,
      "post_id" : 13742322,
      "comment_id" : 77151635,
      "content_license" : "CC BY-SA 3.0",
      "body" : "@AndreasL. httpClient is of type HttpClient ( org.apache.commons.httpclient package)"
    }, {
      "owner" : {
        "account_id" : 176018,
        "reputation" : 55665,
        "user_id" : 406429,
        "user_type" : "registered",
        "profile_image" : "https://www.gravatar.com/avatar/62d4ca92192b41f45829db7b7020ee0e?s=256&d=identicon&r=PG",
        "display_name" : "Claus Ibsen",
        "link" : "https://stackoverflow.com/users/406429/claus-ibsen"
      },
      "edited" : false,
      "score" : 1,
      "creation_date" : 1585163999,
      "post_id" : 13742322,
      "comment_id" : 107670373,
      "content_license" : "CC BY-SA 4.0",
      "body" : "Its so common to get the response content as string or byte array or something. Would be nice with an API directly on Entity to give you that. Having to look for this to find this util class."
    }, {
      "owner" : {
        "account_id" : 74886,
        "reputation" : 28227,
        "user_id" : 214977,
        "user_type" : "registered",
        "accept_rate" : 69,
        "profile_image" : "https://i.sstatic.net/fmJRN.png?s=256",
        "display_name" : "granadaCoder",
        "link" : "https://stackoverflow.com/users/214977/granadacoder"
      },
      "edited" : false,
      "score" : 1,
      "creation_date" : 1611257558,
      "post_id" : 13742322,
      "comment_id" : 116400123,
      "content_license" : "CC BY-SA 4.0",
      "body" : "I upvoted. Please consider adding the full &quot;imports&quot; statements."
    }, {
      "owner" : {
        "account_id" : 15083,
        "reputation" : 22557,
        "user_id" : 31506,
        "user_type" : "registered",
        "profile_image" : "https://www.gravatar.com/avatar/ced11826cb92c2e759c45bef134ca534?s=256&d=identicon&r=PG",
        "display_name" : "Jack Leow",
        "link" : "https://stackoverflow.com/users/31506/jack-leow"
      },
      "edited" : false,
      "score" : 0,
      "creation_date" : 1635255034,
      "post_id" : 13742322,
      "comment_id" : 123243689,
      "content_license" : "CC BY-SA 4.0",
      "body" : "Worth noting that the first method will get you the response body regardless of the HTTP status, whereas the second method throws exception for non-2xx HTTP statuses."
    }, {
      "owner" : {
        "account_id" : 12107061,
        "reputation" : 3510,
        "user_id" : 8845480,
        "user_type" : "registered",
        "profile_image" : "https://i.sstatic.net/HPjMLxOy.png?s=256",
        "display_name" : "rjumatov",
        "link" : "https://stackoverflow.com/users/8845480/rjumatov"
      },
      "edited" : false,
      "score" : 0,
      "creation_date" : 1666959533,
      "post_id" : 13742322,
      "comment_id" : 131063656,
      "content_license" : "CC BY-SA 4.0",
      "body" : "How would you retrieve the response body for non-2xx HTTP statuses?"
    }, {
      "owner" : {
        "account_id" : 18290693,
        "reputation" : 536,
        "user_id" : 13466188,
        "user_type" : "registered",
        "profile_image" : "https://lh3.googleusercontent.com/a-/AOh14GgCSCOX5DuhcpySPcfB0ZTddFk3UUGYXwjG2fH9=k-s256",
        "display_name" : "Prashant Singh",
        "link" : "https://stackoverflow.com/users/13466188/prashant-singh"
      },
      "edited" : false,
      "score" : 0,
      "creation_date" : 1678979309,
      "post_id" : 13742322,
      "comment_id" : 133641243,
      "content_license" : "CC BY-SA 4.0",
      "body" : "I am getting &quot;Attempted read from closed stream.&quot; error while using body = EntityUtils.toString(response.getEntity());"
    }, {
      "owner" : {
        "account_id" : 1886834,
        "reputation" : 566,
        "user_id" : 1705880,
        "user_type" : "registered",
        "accept_rate" : 50,
        "profile_image" : "https://i.sstatic.net/PQ3cs.jpg?s=256",
        "display_name" : "Sparm",
        "link" : "https://stackoverflow.com/users/1705880/sparm"
      },
      "edited" : false,
      "score" : 0,
      "creation_date" : 1690195360,
      "post_id" : 13742322,
      "comment_id" : 135314709,
      "content_license" : "CC BY-SA 4.0",
      "body" : "You should add how you&#39;ve instantiated <code>httpClient</code> as its not necessarily clear to all readers"
    } ],
    "owner" : {
      "account_id" : 2118276,
      "reputation" : 3644,
      "user_id" : 1882094,
      "user_type" : "registered",
      "profile_image" : "https://www.gravatar.com/avatar/ed08f34076746a286a31b1e3a8cbfe6a?s=256&d=identicon&r=PG",
      "display_name" : "spideringweb",
      "link" : "https://stackoverflow.com/users/1882094/spideringweb"
    },
    "is_accepted" : false,
    "score" : 346,
    "last_activity_date" : 1396635833,
    "last_edit_date" : 1396635833,
    "creation_date" : 1354792102,
    "answer_id" : 13742322,
    "question_id" : 5769717,
    "content_license" : "CC BY-SA 3.0",
    "body" : "<p>Here are two examples from my working project. </p>\n\n<ol>\n<li><p>Using <a href=\"http://hc.apache.org/httpcomponents-core-ga/httpcore/apidocs/org/apache/http/util/EntityUtils.html\"><code>EntityUtils</code></a> and <a href=\"http://hc.apache.org/httpcomponents-core-ga/httpcore/apidocs/org/apache/http/HttpEntity.html\"><code>HttpEntity</code></a></p>\n\n<pre><code>HttpResponse response = httpClient.execute(new HttpGet(URL));\nHttpEntity entity = response.getEntity();\nString responseString = EntityUtils.toString(entity, \"UTF-8\");\nSystem.out.println(responseString);\n</code></pre></li>\n<li><p>Using <a href=\"http://hc.apache.org/httpcomponents-client-ga/httpclient/apidocs/org/apache/http/impl/client/BasicResponseHandler.html\"><code>BasicResponseHandler</code></a></p>\n\n<pre><code>HttpResponse response = httpClient.execute(new HttpGet(URL));\nString responseString = new BasicResponseHandler().handleResponse(response);\nSystem.out.println(responseString);\n</code></pre></li>\n</ol>\n"
  }, {
    "owner" : {
      "account_id" : 927098,
      "reputation" : 815,
      "user_id" : 957658,
      "user_type" : "registered",
      "accept_rate" : 92,
      "profile_image" : "https://www.gravatar.com/avatar/48f3fd6e45a5bb9fac5e53025c8b6961?s=256&d=identicon&r=PG",
      "display_name" : "Akshay",
      "link" : "https://stackoverflow.com/users/957658/akshay"
    },
    "is_accepted" : false,
    "score" : 10,
    "last_activity_date" : 1398416238,
    "last_edit_date" : 1398416238,
    "creation_date" : 1395981144,
    "answer_id" : 22704262,
    "question_id" : 5769717,
    "content_license" : "CC BY-SA 3.0",
    "body" : "<p>The Answer by McDowell is correct one. However if you try other suggestion in few of the posts above.</p>\n\n<pre><code>HttpEntity responseEntity = httpResponse.getEntity();\nif(responseEntity!=null) {\n   response = EntityUtils.toString(responseEntity);\n   S.O.P (response);\n}\n</code></pre>\n\n<p>Then it will give you illegalStateException stating that content is already consumed.</p>\n"
  }, {
    "owner" : {
      "account_id" : 3045270,
      "reputation" : 3978,
      "user_id" : 2581128,
      "user_type" : "registered",
      "profile_image" : "https://i.sstatic.net/oKiuF.jpg?s=256",
      "display_name" : "lkamal",
      "link" : "https://stackoverflow.com/users/2581128/lkamal"
    },
    "is_accepted" : false,
    "score" : 11,
    "last_activity_date" : 1452593165,
    "creation_date" : 1452593165,
    "answer_id" : 34740645,
    "question_id" : 5769717,
    "content_license" : "CC BY-SA 3.0",
    "body" : "<p>Below is a simple way of accessing the response as a String using Apache HTTP Client library.</p>\n\n<pre><code>import org.apache.http.HttpResponse;\nimport org.apache.http.client.HttpClient;\nimport org.apache.http.client.ResponseHandler;\nimport org.apache.http.client.methods.HttpGet;\nimport org.apache.http.impl.client.BasicResponseHandler;\n\n//... \n\nHttpGet get;\nHttpClient httpClient;\n\n// initialize variables above\n\nResponseHandler&lt;String&gt; responseHandler = new BasicResponseHandler();\nString responseBody = httpClient.execute(get, responseHandler);\n</code></pre>\n"
  }, {
    "comments" : [ {
      "owner" : {
        "account_id" : 2966321,
        "reputation" : 3614,
        "user_id" : 2519395,
        "user_type" : "registered",
        "accept_rate" : 76,
        "profile_image" : "https://i.sstatic.net/8BTlv.jpg?s=256",
        "display_name" : "SlimenTN",
        "link" : "https://stackoverflow.com/users/2519395/slimentn"
      },
      "edited" : false,
      "score" : 0,
      "creation_date" : 1514800452,
      "post_id" : 41327618,
      "comment_id" : 83068835,
      "content_license" : "CC BY-SA 3.0",
      "body" : "This is a very good response, this is what I need to display, the response after posting data to the server. Well done."
    } ],
    "owner" : {
      "account_id" : 7508134,
      "reputation" : 1337,
      "user_id" : 5704042,
      "user_type" : "registered",
      "profile_image" : "https://lh3.googleusercontent.com/-FxQmS38fzuo/AAAAAAAAAAI/AAAAAAAAABA/Q5kv5yb_t8A/s256-rj/photo.jpg",
      "display_name" : "Subhasish Sahu",
      "link" : "https://stackoverflow.com/users/5704042/subhasish-sahu"
    },
    "is_accepted" : false,
    "score" : 3,
    "last_activity_date" : 1486354766,
    "last_edit_date" : 1486354766,
    "creation_date" : 1482735915,
    "answer_id" : 41327618,
    "question_id" : 5769717,
    "content_license" : "CC BY-SA 3.0",
    "body" : "<p>We can use the below code also to get the HTML Response in java</p>\n\n<pre><code>import org.apache.http.client.HttpClient;\nimport org.apache.http.client.methods.HttpGet;\nimport org.apache.http.impl.client.DefaultHttpClient;\nimport org.apache.http.HttpResponse;\nimport java.io.BufferedReader;\nimport java.io.InputStreamReader;\nimport org.apache.log4j.Logger;\n\npublic static void main(String[] args) throws Exception {\n    HttpClient client = new DefaultHttpClient();\n    //  args[0] :-  http://hostname:8080/abc/xyz/CheckResponse\n    HttpGet request1 = new HttpGet(args[0]);\n    HttpResponse response1 = client.execute(request1);\n    int code = response1.getStatusLine().getStatusCode();\n\n    try (BufferedReader br = new BufferedReader(new InputStreamReader((response1.getEntity().getContent())));) {\n        // Read in all of the post results into a String.\n        String output = \"\";\n        Boolean keepGoing = true;\n        while (keepGoing) {\n            String currentLine = br.readLine();\n\n            if (currentLine == null) {\n                keepGoing = false;\n            } else {\n                output += currentLine;\n            }\n        }\n\n        System.out.println(\"Response--&gt;\" + output);\n    } catch (Exception e) {\n        System.out.println(\"Exception\" + e);\n\n    }\n}\n</code></pre>\n"
  }, {
    "owner" : {
      "account_id" : 4105113,
      "reputation" : 333,
      "user_id" : 7962741,
      "user_type" : "registered",
      "profile_image" : "https://i.sstatic.net/jB07N.png?s=256",
      "display_name" : "Marko Zajc",
      "link" : "https://stackoverflow.com/users/7962741/marko-zajc"
    },
    "is_accepted" : false,
    "score" : 2,
    "last_activity_date" : 1505744956,
    "creation_date" : 1505744956,
    "answer_id" : 46281854,
    "question_id" : 5769717,
    "content_license" : "CC BY-SA 3.0",
    "body" : "<p>Here's a lightweight way to do so:</p>\n\n<pre><code>String responseString = \"\";\nfor (int i = 0; i &lt; response.getEntity().getContentLength(); i++) { \n    responseString +=\n    Character.toString((char)response.getEntity().getContent().read()); \n}\n</code></pre>\n\n<p>With of course <code>responseString</code> containing website's response and response being type of <code>HttpResponse</code>, returned by <code>HttpClient.execute(request)</code></p>\n"
  }, {
    "owner" : {
      "account_id" : 7200064,
      "reputation" : 1207,
      "user_id" : 5497548,
      "user_type" : "registered",
      "profile_image" : "https://i.sstatic.net/IrHVH.jpg?s=256",
      "display_name" : "Krutik",
      "link" : "https://stackoverflow.com/users/5497548/krutik"
    },
    "is_accepted" : false,
    "score" : 1,
    "last_activity_date" : 1544603343,
    "creation_date" : 1544603343,
    "answer_id" : 53738906,
    "question_id" : 5769717,
    "content_license" : "CC BY-SA 4.0",
    "body" : "<p>Following is the code snippet which shows better way to handle the response body as a String whether it's a valid response or error response for the HTTP POST request:</p>\n\n<pre><code>BufferedReader reader = null;\nOutputStream os = null;\nString payload = \"\";\ntry {\n    URL url1 = new URL(\"YOUR_URL\");\n    HttpURLConnection postConnection = (HttpURLConnection) url1.openConnection();\n    postConnection.setRequestMethod(\"POST\");\n    postConnection.setRequestProperty(\"Content-Type\", \"application/json\");\n    postConnection.setDoOutput(true);\n    os = postConnection.getOutputStream();\n    os.write(eventContext.getMessage().getPayloadAsString().getBytes());\n    os.flush();\n\n    String line;\n    try{\n        reader = new BufferedReader(new InputStreamReader(postConnection.getInputStream()));\n    }\n    catch(IOException e){\n        if(reader == null)\n            reader = new BufferedReader(new InputStreamReader(postConnection.getErrorStream()));\n    }\n    while ((line = reader.readLine()) != null)\n        payload += line.toString();\n}       \ncatch (Exception ex) {\n            log.error(\"Post request Failed with message: \" + ex.getMessage(), ex);\n} finally {\n    try {\n        reader.close();\n        os.close();\n    } catch (IOException e) {\n        log.error(e.getMessage(), e);\n        return null;\n    }\n}\n</code></pre>\n"
  }, {
    "owner" : {
      "account_id" : 2316085,
      "reputation" : 10676,
      "user_id" : 2873507,
      "user_type" : "registered",
      "accept_rate" : 70,
      "profile_image" : "https://i.sstatic.net/FRWzZ.png?s=256",
      "display_name" : "Vic Seedoubleyew",
      "link" : "https://stackoverflow.com/users/2873507/vic-seedoubleyew"
    },
    "is_accepted" : false,
    "score" : 0,
    "last_activity_date" : 1562340705,
    "creation_date" : 1562340705,
    "answer_id" : 56905864,
    "question_id" : 5769717,
    "content_license" : "CC BY-SA 4.0",
    "body" : "<p>If you are using Jackson to deserialize the response body, one very simple solution is to use <code>request.getResponseBodyAsStream()</code> instead of <strike><code>request.getResponseBodyAsString()</code></strike></p>\n"
  }, {
    "comments" : [ {
      "owner" : {
        "account_id" : 987434,
        "reputation" : 12596,
        "user_id" : 1005607,
        "user_type" : "registered",
        "accept_rate" : 64,
        "profile_image" : "https://www.gravatar.com/avatar/784311347e657bc34c93a6b7cb7d3faf?s=256&d=identicon&r=PG",
        "display_name" : "gene b.",
        "link" : "https://stackoverflow.com/users/1005607/gene-b"
      },
      "edited" : false,
      "score" : 0,
      "creation_date" : 1698543880,
      "post_id" : 66345424,
      "comment_id" : 136418824,
      "content_license" : "CC BY-SA 4.0",
      "body" : "One correction! <code>.uri(URI.create(targetUrl))</code>, not <code>.uri(targetUrl)</code> !"
    } ],
    "owner" : {
      "account_id" : 114116,
      "reputation" : 39874,
      "user_id" : 300224,
      "user_type" : "registered",
      "accept_rate" : 68,
      "profile_image" : "https://i.sstatic.net/N5nuc.jpg?s=256",
      "display_name" : "William Entriken",
      "link" : "https://stackoverflow.com/users/300224/william-entriken"
    },
    "is_accepted" : false,
    "score" : 4,
    "last_activity_date" : 1614146124,
    "creation_date" : 1614146124,
    "answer_id" : 66345424,
    "question_id" : 5769717,
    "content_license" : "CC BY-SA 4.0",
    "body" : "<p>Here is a vanilla Java answer:</p>\n<pre class=\"lang-java prettyprint-override\"><code>import java.net.http.HttpClient;\nimport java.net.http.HttpResponse;\nimport java.net.http.HttpRequest;\nimport java.net.http.HttpRequest.BodyPublishers;\n\n...\nHttpClient client = HttpClient.newHttpClient();\nHttpRequest request = HttpRequest.newBuilder()\n  .uri(targetUrl)\n  .header(&quot;Content-Type&quot;, &quot;application/json&quot;)\n  .POST(BodyPublishers.ofString(requestBody))\n  .build();\nHttpResponse response = client.send(request, HttpResponse.BodyHandlers.ofString());\nString responseString = (String) response.body();\n</code></pre>\n"
  }, {
    "owner" : {
      "account_id" : 7339562,
      "reputation" : 628,
      "user_id" : 5589683,
      "user_type" : "registered",
      "profile_image" : "https://lh5.googleusercontent.com/-jvQwFihm06c/AAAAAAAAAAI/AAAAAAAAAD8/y2WpUc5w2Tk/s256-rj/photo.jpg",
      "display_name" : "pratap",
      "link" : "https://stackoverflow.com/users/5589683/pratap"
    },
    "is_accepted" : false,
    "score" : -1,
    "last_activity_date" : 1620203807,
    "creation_date" : 1620203807,
    "answer_id" : 67397820,
    "question_id" : 5769717,
    "content_license" : "CC BY-SA 4.0",
    "body" : "<p>Using Apache commons Fluent API, it can be done as mentioned below,</p>\n<pre><code>String response = Request.Post(&quot;http://www.example.com/&quot;)\n                .body(new StringEntity(strbody))\n                .addHeader(&quot;Accept&quot;,&quot;application/json&quot;)\n                .addHeader(&quot;Content-Type&quot;,&quot;application/json&quot;)\n                .execute().returnContent().asString();\n</code></pre>\n"
  } ],
  "owner" : {
    "account_id" : 373070,
    "reputation" : 2434,
    "user_id" : 722477,
    "user_type" : "registered",
    "accept_rate" : 100,
    "profile_image" : "https://www.gravatar.com/avatar/268e3b98abe8395b2b3195c66bbeb382?s=256&d=identicon&r=PG",
    "display_name" : "Daniel Shaulov",
    "link" : "https://stackoverflow.com/users/722477/daniel-shaulov"
  },
  "is_answered" : true,
  "view_count" : 682436,
  "accepted_answer_id" : 5769756,
  "answer_count" : 13,
  "score" : 200,
  "last_activity_date" : 1620203807,
  "creation_date" : 1303637138,
  "last_edit_date" : 1613638309,
  "question_id" : 5769717,
  "link" : "https://stackoverflow.com/questions/5769717/how-can-i-get-an-http-response-body-as-a-string",
  "title" : "How can I get an HTTP response body as a string?",
  "body" : "<p>I know there used to be a way to get it with Apache Commons as documented here:</p>\n<p><a href=\"http://hc.apache.org/httpclient-legacy/apidocs/org/apache/commons/httpclient/HttpMethod.html\" rel=\"noreferrer\">http://hc.apache.org/httpclient-legacy/apidocs/org/apache/commons/httpclient/HttpMethod.html</a></p>\n<p>...and an example here:</p>\n<p><a href=\"http://www.kodejava.org/examples/416.html\" rel=\"noreferrer\">http://www.kodejava.org/examples/416.html</a></p>\n<p>...but I believe this is deprecated.</p>\n<p>Is there any other way to make an http get request in Java and get the response body as a string and not a stream?</p>\n"
}