{
  "tags" : [ "java", "android", "encryption", "preferences", "credentials" ],
  "answers" : [ {
    "comments" : [ {
      "owner" : {
        "account_id" : 457161,
        "reputation" : 5133,
        "user_id" : 856307,
        "user_type" : "registered",
        "accept_rate" : 100,
        "profile_image" : "https://www.gravatar.com/avatar/7efbe3883af07b10ecef5192a6962f17?s=256&d=identicon&r=PG",
        "display_name" : "Abhijit",
        "link" : "https://stackoverflow.com/users/856307/abhijit"
      },
      "edited" : false,
      "score" : 3,
      "creation_date" : 1341327604,
      "post_id" : 786588,
      "comment_id" : 14889254,
      "content_license" : "CC BY-SA 3.0",
      "body" : "Could you please explain what you mean by sandboxed?"
    }, {
      "owner" : {
        "account_id" : 305838,
        "reputation" : 6647,
        "user_id" : 616225,
        "user_type" : "registered",
        "accept_rate" : 86,
        "profile_image" : "https://www.gravatar.com/avatar/ca6e421b31f38e89b1b9dcd9978844b7?s=256&d=identicon&r=PG",
        "display_name" : "Sergi Juanola",
        "link" : "https://stackoverflow.com/users/616225/sergi-juanola"
      },
      "edited" : false,
      "score" : 16,
      "creation_date" : 1342126000,
      "post_id" : 786588,
      "comment_id" : 15127680,
      "content_license" : "CC BY-SA 3.0",
      "body" : "a sandboxed program is any application whose process and information (such as those shared preferences) remains hidden from the rest of the applications. An android application running in a package cannot directly access to anything inside another package. That&#39;s why applications in the same package (which are always yours) could access to information from other ones"
    }, {
      "owner" : {
        "account_id" : 1313894,
        "reputation" : 25898,
        "user_id" : 1261266,
        "user_type" : "registered",
        "accept_rate" : 53,
        "profile_image" : "https://i.sstatic.net/ObH7b.jpg?s=256",
        "display_name" : "Piyush Agarwal",
        "link" : "https://stackoverflow.com/users/1261266/piyush-agarwal"
      },
      "edited" : false,
      "score" : 0,
      "creation_date" : 1363031240,
      "post_id" : 786588,
      "comment_id" : 21678445,
      "content_license" : "CC BY-SA 3.0",
      "body" : "@Reto Meier my requirement is to protect the publicly available web services for that I am using a token, is storing it on shared preferences is safe?  i have a bootup broadcast receiver in my application which will delete all sharedpreferences data if it found device as rooted. Is this enough to protect my token."
    }, {
      "owner" : {
        "account_id" : 923404,
        "reputation" : 8064,
        "user_id" : 954643,
        "user_type" : "registered",
        "accept_rate" : 80,
        "profile_image" : "https://www.gravatar.com/avatar/4179aad8a57c39de31d8ef12a9bf7e84?s=256&d=identicon&r=PG",
        "display_name" : "qix",
        "link" : "https://stackoverflow.com/users/954643/qix"
      },
      "edited" : false,
      "score" : 1,
      "creation_date" : 1382126761,
      "post_id" : 786588,
      "comment_id" : 28853953,
      "content_license" : "CC BY-SA 3.0",
      "body" : "Per <a href=\"http://android-developers.blogspot.com/2013/02/using-cryptography-to-store-credentials.html\" rel=\"nofollow noreferrer\">android-developers.blogspot.com/2013/02/&hellip;</a>, <i>User credentials should be stored with the MODE_PRIVATE flag set and stored in internal storage</i> (with the same caveats about storing any sort of password locally ultimately open to attack). That said, is using <code>MODE_PRIVATE</code> with SharedPreferences equivalent to doing the same with a file created on internal storage, in terms of effectiveness to obfuscate locally stored data?"
    }, {
      "owner" : {
        "account_id" : 1790714,
        "reputation" : 94737,
        "user_id" : 1631193,
        "user_type" : "registered",
        "accept_rate" : 71,
        "profile_image" : "https://www.gravatar.com/avatar/ac9dfee58394495fa69f12f58a928be3?s=256&d=identicon&r=PG&f=y&so-version=2",
        "display_name" : "Gabe Sechan",
        "link" : "https://stackoverflow.com/users/1631193/gabe-sechan"
      },
      "edited" : false,
      "score" : 9,
      "creation_date" : 1406428282,
      "post_id" : 786588,
      "comment_id" : 38827672,
      "content_license" : "CC BY-SA 3.0",
      "body" : "Do not store a password in shared preferences. If the user ever loses the phone, they&#39;ve lost the password. It will be read. If they used that password elsewhere, everyplace they used it is compromised. In addition, you&#39;ve permanently lost this account because with the password they can change your password. The correct way to do this is to send the password up to the server once, and receive a login token back. Store that in shared preference and send it up with each request. If that token is compromised, nothing else is lost."
    }, {
      "owner" : {
        "account_id" : 378218,
        "reputation" : 32450,
        "user_id" : 730807,
        "user_type" : "registered",
        "accept_rate" : 62,
        "profile_image" : "https://i.sstatic.net/HKPf2.png?s=256",
        "display_name" : "Durai Amuthan.H",
        "link" : "https://stackoverflow.com/users/730807/durai-amuthan-h"
      },
      "edited" : false,
      "score" : 0,
      "creation_date" : 1417127176,
      "post_id" : 786588,
      "comment_id" : 42847648,
      "content_license" : "CC BY-SA 3.0",
      "body" : "Speaking of storing the credentials safely.Read this <a href=\"http://stackoverflow.com/a/20560574/730807\">stackoverflow.com/a/20560574/730807</a>"
    }, {
      "owner" : {
        "account_id" : 294560,
        "reputation" : 4328,
        "user_id" : 598520,
        "user_type" : "registered",
        "accept_rate" : 100,
        "profile_image" : "https://i.sstatic.net/MH4aH.jpg?s=256",
        "display_name" : "Guillaume Perrot",
        "link" : "https://stackoverflow.com/users/598520/guillaume-perrot"
      },
      "edited" : false,
      "score" : 0,
      "creation_date" : 1485473746,
      "post_id" : 786588,
      "comment_id" : 70952204,
      "content_license" : "CC BY-SA 3.0",
      "body" : "@reto-meier &quot;At the very least, make sure you&#39;re encrypting the password before writing it to disk.&quot; How do you access or store the encryption key in that case? If you have to retrieve the key from the server every time, how can you possibly retrieve it (in a secure way) without requiring the user to log in interactively (which defeats the purpose of remembering credentials to avoid login). How do you prevent a rooted device to heap dump your application and finding the encryption key?"
    }, {
      "owner" : {
        "account_id" : 17029695,
        "reputation" : 2157,
        "user_id" : 12320109,
        "user_type" : "registered",
        "profile_image" : "https://i.sstatic.net/4K1F2.jpg?s=256",
        "display_name" : "Boommeister",
        "link" : "https://stackoverflow.com/users/12320109/boommeister"
      },
      "edited" : false,
      "score" : 0,
      "creation_date" : 1608017633,
      "post_id" : 786588,
      "comment_id" : 115446220,
      "content_license" : "CC BY-SA 4.0",
      "body" : "@Reto Meier I store the user&#39;s email &amp; password encrypted in shared preferences, is there a place where I can put my key? I&#39;m searching for something like a password/keymanager: The user unlocks his phone with his pin -&gt; the pin gets used to automatically decrypt the keymanager -&gt; all apps can access their own keys now to decrypt their shared preference values. -&gt; when the phone gets locked, the keymanager gets encrypted automatically. Now my shared preferences would be safe, even when the device gets rooted, no? I&#39;m new to app development, but if something like this doesn&#39;t exist, why not?"
    }, {
      "owner" : {
        "account_id" : 17029695,
        "reputation" : 2157,
        "user_id" : 12320109,
        "user_type" : "registered",
        "profile_image" : "https://i.sstatic.net/4K1F2.jpg?s=256",
        "display_name" : "Boommeister",
        "link" : "https://stackoverflow.com/users/12320109/boommeister"
      },
      "edited" : false,
      "score" : 0,
      "creation_date" : 1608017801,
      "post_id" : 786588,
      "comment_id" : 115446279,
      "content_license" : "CC BY-SA 4.0",
      "body" : "I know a 4 char pin is not safe against brute attacks, but many phones use fingerprint or face recognition. You could tell the users, if they want to keep using a pin they should consider using a longer one. I mean even with a 4 char pin it would be at least an additional security measure at zero loss to UX."
    } ],
    "owner" : {
      "account_id" : 629,
      "reputation" : 96886,
      "user_id" : 822,
      "user_type" : "registered",
      "profile_image" : "https://www.gravatar.com/avatar/4fb837e697c4142468b05c8f34e1cc49?s=256&d=identicon&r=PG",
      "display_name" : "Reto Meier",
      "link" : "https://stackoverflow.com/users/822/reto-meier"
    },
    "is_accepted" : true,
    "score" : 242,
    "last_activity_date" : 1240590035,
    "creation_date" : 1240590035,
    "answer_id" : 786588,
    "question_id" : 785973,
    "content_license" : "CC BY-SA 2.5",
    "body" : "<p>In general SharedPreferences are your best bet for storing preferences, so in general I'd recommend that approach for saving application and user settings.</p>\n\n<p>The only area of concern here is what you're saving. Passwords are always a tricky thing to store, and I'd be particularly wary of storing them as clear text. The Android architecture is such that your application's SharedPreferences are sandboxed to prevent other applications from being able to access the values so there's some security there, but physical access to a phone could potentially allow access to the values.</p>\n\n<p>If possible I'd consider modifying the server to use a negotiated token for providing access, something like <a href=\"http://code.google.com/p/oauth/\" rel=\"noreferrer\">OAuth</a>. Alternatively you may need to construct some sort of cryptographic store, though that's non-trivial. At the very least, make sure you're encrypting the password before writing it to disk.</p>\n"
  }, {
    "comments" : [ {
      "owner" : {
        "account_id" : 111824,
        "reputation" : 4268,
        "user_id" : 295199,
        "user_type" : "registered",
        "accept_rate" : 100,
        "profile_image" : "https://www.gravatar.com/avatar/81e17d5ea1fc5372e8985ea3dd9dc241?s=256&d=identicon&r=PG",
        "display_name" : "HXCaine",
        "link" : "https://stackoverflow.com/users/295199/hxcaine"
      },
      "edited" : false,
      "score" : 4,
      "creation_date" : 1274797673,
      "post_id" : 792396,
      "comment_id" : 2955500,
      "content_license" : "CC BY-SA 2.5",
      "body" : "The OP needs to store one username and password pair. It would be ridiculous to consider creating an entire database table for this one use"
    }, {
      "owner" : {
        "account_id" : 1194778,
        "reputation" : 9584,
        "user_id" : 1166727,
        "user_type" : "registered",
        "accept_rate" : 65,
        "profile_image" : "https://i.sstatic.net/xPfWn.jpg?s=256",
        "display_name" : "tony gil",
        "link" : "https://stackoverflow.com/users/1166727/tony-gil"
      },
      "reply_to_user" : {
        "account_id" : 111824,
        "reputation" : 4268,
        "user_id" : 295199,
        "user_type" : "registered",
        "accept_rate" : 100,
        "profile_image" : "https://www.gravatar.com/avatar/81e17d5ea1fc5372e8985ea3dd9dc241?s=256&d=identicon&r=PG",
        "display_name" : "HXCaine",
        "link" : "https://stackoverflow.com/users/295199/hxcaine"
      },
      "edited" : false,
      "score" : 0,
      "creation_date" : 1342968019,
      "post_id" : 792396,
      "comment_id" : 15356004,
      "content_license" : "CC BY-SA 3.0",
      "body" : "@HXCaine i respectfully disagree - i can see at least 1 other use of a user/passwords sqlite table.  IF YOU CONSIDER THE RISK (of using sqlite) ACCEPTABLE, besides simple application login authentication, you could use the table to store multiple ftp passwords (if your app uses ftp - mine do sometimes), for example.  plus, creating a sqlite adapter class for this manipulation is boilerplate simple."
    }, {
      "owner" : {
        "account_id" : 111824,
        "reputation" : 4268,
        "user_id" : 295199,
        "user_type" : "registered",
        "accept_rate" : 100,
        "profile_image" : "https://www.gravatar.com/avatar/81e17d5ea1fc5372e8985ea3dd9dc241?s=256&d=identicon&r=PG",
        "display_name" : "HXCaine",
        "link" : "https://stackoverflow.com/users/295199/hxcaine"
      },
      "edited" : false,
      "score" : 0,
      "creation_date" : 1343163690,
      "post_id" : 792396,
      "comment_id" : 15417963,
      "content_license" : "CC BY-SA 3.0",
      "body" : "Nice resurrection of a two-year-old comment! To be fair, my comment was a year after the answer :) Even with a handful of FTP passwords, the overhead is much larger with an SQLite table than with SharedPreferences both in terms of space and coding. Surely that can&#39;t be necessary"
    } ],
    "owner" : {
      "user_type" : "does_not_exist",
      "display_name" : "xyz"
    },
    "is_accepted" : false,
    "score" : -3,
    "last_activity_date" : 1260521140,
    "last_edit_date" : 1260521140,
    "creation_date" : 1240812584,
    "answer_id" : 792396,
    "question_id" : 785973,
    "content_license" : "CC BY-SA 2.5",
    "body" : "<p>you need to use the sqlite, security apit to store the passwords.\nhere is best example, which stores passwords, -- passwordsafe.\nhere is link for the source and explanation -- \n<a href=\"http://code.google.com/p/android-passwordsafe/\" rel=\"nofollow noreferrer\">http://code.google.com/p/android-passwordsafe/</a></p>\n"
  }, {
    "comments" : [ {
      "owner" : {
        "account_id" : 341305,
        "reputation" : 1565,
        "user_id" : 671827,
        "user_type" : "registered",
        "accept_rate" : 55,
        "profile_image" : "https://www.gravatar.com/avatar/fdd49c2310be1ef3a4f7c1a61f579498?s=256&d=identicon&r=PG",
        "display_name" : "While-E",
        "link" : "https://stackoverflow.com/users/671827/while-e"
      },
      "reply_to_user" : {
        "account_id" : 28682,
        "reputation" : 47584,
        "user_id" : 76835,
        "user_type" : "registered",
        "accept_rate" : 78,
        "profile_image" : "https://www.gravatar.com/avatar/67e30611a423f3bf36c1fc65fd392bfb?s=256&d=identicon&r=PG",
        "display_name" : "Jeremy Logan",
        "link" : "https://stackoverflow.com/users/76835/jeremy-logan"
      },
      "edited" : false,
      "score" : 9,
      "creation_date" : 1308198112,
      "post_id" : 819320,
      "comment_id" : 7455717,
      "content_license" : "CC BY-SA 3.0",
      "body" : "I couldn&#39;t agree with you more about this simplistic approach; however, you should always be worried about the security of passwords that you store? Depending on your application, you have potential liabilities for stolen personal information. Just pointing this out for anybody trying to store actual passwords to such things as bank accounts or something equally important. I still vote you though."
    }, {
      "owner" : {
        "account_id" : 894800,
        "reputation" : 1409,
        "user_id" : 932324,
        "user_type" : "registered",
        "accept_rate" : 94,
        "profile_image" : "https://www.gravatar.com/avatar/a291aa9f2439a0ce0f27a918757df218?s=256&d=identicon&r=PG",
        "display_name" : "OrhanC1",
        "link" : "https://stackoverflow.com/users/932324/orhanc1"
      },
      "edited" : false,
      "score" : 2,
      "creation_date" : 1407420529,
      "post_id" : 819320,
      "comment_id" : 39215183,
      "content_license" : "CC BY-SA 3.0",
      "body" : "Where would you store the key that stored the password? If the shared preferences are accessible by other users, so is the key."
    }, {
      "owner" : {
        "account_id" : 7937045,
        "reputation" : 3351,
        "user_id" : 5992618,
        "user_type" : "registered",
        "accept_rate" : 75,
        "profile_image" : "https://i.sstatic.net/VzTcn.jpg?s=256",
        "display_name" : "eRaisedToX",
        "link" : "https://stackoverflow.com/users/5992618/eraisedtox"
      },
      "reply_to_user" : {
        "account_id" : 894800,
        "reputation" : 1409,
        "user_id" : 932324,
        "user_type" : "registered",
        "accept_rate" : 94,
        "profile_image" : "https://www.gravatar.com/avatar/a291aa9f2439a0ce0f27a918757df218?s=256&d=identicon&r=PG",
        "display_name" : "OrhanC1",
        "link" : "https://stackoverflow.com/users/932324/orhanc1"
      },
      "edited" : false,
      "score" : 0,
      "creation_date" : 1503144252,
      "post_id" : 819320,
      "comment_id" : 78500718,
      "content_license" : "CC BY-SA 3.0",
      "body" : "@OrhanC1 did you get the answer.?"
    }, {
      "owner" : {
        "user_type" : "does_not_exist",
        "display_name" : "user19309143"
      },
      "reply_to_user" : {
        "account_id" : 7937045,
        "reputation" : 3351,
        "user_id" : 5992618,
        "user_type" : "registered",
        "accept_rate" : 75,
        "profile_image" : "https://i.sstatic.net/VzTcn.jpg?s=256",
        "display_name" : "eRaisedToX",
        "link" : "https://stackoverflow.com/users/5992618/eraisedtox"
      },
      "edited" : false,
      "score" : 0,
      "creation_date" : 1656710802,
      "post_id" : 819320,
      "comment_id" : 128646930,
      "content_license" : "CC BY-SA 4.0",
      "body" : "@eRaisedToX The answer is there is no answer. <a href=\"https://developer.android.com/reference/androidx/security/crypto/EncryptedSharedPreferences\" rel=\"nofollow noreferrer\">EnryptedSharedPreferences</a> even runs into this problem when it stores the encryption key in KeyStore. As long as the encryption key is on the device, the data is vulnerable. The only semi-solution is to put the key on a server, but that means the key must exist in the device at some point (either in storage or in memory)."
    } ],
    "owner" : {
      "account_id" : 28682,
      "reputation" : 47584,
      "user_id" : 76835,
      "user_type" : "registered",
      "accept_rate" : 78,
      "profile_image" : "https://www.gravatar.com/avatar/67e30611a423f3bf36c1fc65fd392bfb?s=256&d=identicon&r=PG",
      "display_name" : "Jeremy Logan",
      "link" : "https://stackoverflow.com/users/76835/jeremy-logan"
    },
    "is_accepted" : false,
    "score" : 29,
    "last_activity_date" : 1403112382,
    "last_edit_date" : 1403112382,
    "creation_date" : 1241427026,
    "answer_id" : 819320,
    "question_id" : 785973,
    "content_license" : "CC BY-SA 3.0",
    "body" : "<p>About the simplest way to store a single preference in an Android Activity is to do something like this:</p>\n\n<pre><code>Editor e = this.getPreferences(Context.MODE_PRIVATE).edit();\ne.putString(\"password\", mPassword);\ne.commit();\n</code></pre>\n\n<p>If you're worried about the security of these then you could always encrypt the password before storing it.</p>\n"
  }, {
    "comments" : [ {
      "owner" : {
        "account_id" : 92694,
        "reputation" : 11726,
        "user_id" : 253938,
        "user_type" : "registered",
        "accept_rate" : 81,
        "profile_image" : "https://www.gravatar.com/avatar/f56facf7921f4e2fbc9a38ca609cbf6b?s=256&d=identicon&r=PG",
        "display_name" : "RenniePet",
        "link" : "https://stackoverflow.com/users/253938/renniepet"
      },
      "edited" : false,
      "score" : 0,
      "creation_date" : 1378435826,
      "post_id" : 5169262,
      "comment_id" : 27460189,
      "content_license" : "CC BY-SA 3.0",
      "body" : "I know this is pretty old, but would you mind posting your code for your custom version of EditTextPreference, please?"
    }, {
      "owner" : {
        "account_id" : 92694,
        "reputation" : 11726,
        "user_id" : 253938,
        "user_type" : "registered",
        "accept_rate" : 81,
        "profile_image" : "https://www.gravatar.com/avatar/f56facf7921f4e2fbc9a38ca609cbf6b?s=256&d=identicon&r=PG",
        "display_name" : "RenniePet",
        "link" : "https://stackoverflow.com/users/253938/renniepet"
      },
      "edited" : false,
      "score" : 0,
      "creation_date" : 1378443848,
      "post_id" : 5169262,
      "comment_id" : 27462082,
      "content_license" : "CC BY-SA 3.0",
      "body" : "Never mind, I found a usable sample here <a href=\"https://groups.google.com/forum/#!topic/android-developers/pMYNEVXMa6M\" rel=\"nofollow noreferrer\">groups.google.com/forum/#!topic/android-developers/pMYNEVXMa&zwnj;&#8203;6M</a> and I&#39;ve got it working now. Thanks for suggesting this approach."
    } ],
    "owner" : {
      "account_id" : 140804,
      "reputation" : 2582,
      "user_id" : 347379,
      "user_type" : "registered",
      "accept_rate" : 93,
      "profile_image" : "https://www.gravatar.com/avatar/b96839224bb9e3bd26f52e49368fef8c?s=256&d=identicon&r=PG",
      "display_name" : "Mark",
      "link" : "https://stackoverflow.com/users/347379/mark"
    },
    "is_accepted" : false,
    "score" : 10,
    "last_activity_date" : 1457958981,
    "last_edit_date" : 1457958981,
    "creation_date" : 1299077786,
    "answer_id" : 5169262,
    "question_id" : 785973,
    "content_license" : "CC BY-SA 3.0",
    "body" : "<p>Using the snippet provided by Richard, you can encrypt the password before saving it.  The preferences API however doesn't provide an easy way to intercept the value and encrypt it - you can block it being saved via an OnPreferenceChange listener, and you theoretically could modify it through a preferenceChangeListener, but that results in an endless loop.</p>\n\n<p>I had earlier suggested adding a \"hidden\" preference in order to accomplish this.  It's definitely not the best way.  I'm going to present two other options that I consider to be more viable. </p>\n\n<p>First, the simplest, is in a preferenceChangeListener, you can grab the entered value, encrypt it, and then save it to an alternative preferences file:</p>\n\n<pre><code>  public boolean onPreferenceChange(Preference preference, Object newValue) {\n      // get our \"secure\" shared preferences file.\n      SharedPreferences secure = context.getSharedPreferences(\n         \"SECURE\",\n         Context.MODE_PRIVATE\n      );\n      String encryptedText = null;\n      // encrypt and set the preference.\n      try {\n         encryptedText = SimpleCrypto.encrypt(Preferences.SEED,(String)newValue);\n\n         Editor editor = secure.getEditor();\n         editor.putString(\"encryptedPassword\",encryptedText);\n         editor.commit();\n      }\n      catch (Exception e) {\n         e.printStackTrace();\n      }\n      // always return false.\n      return false; \n   }\n</code></pre>\n\n<p>The second way, and the way I now prefer, is to create your own custom preference, extending EditTextPreference, @Override'ing the <code>setText()</code> and <code>getText()</code> methods, so that <code>setText()</code> encrypts the password, and <code>getText()</code> returns null.</p>\n"
  }, {
    "comments" : [ {
      "owner" : {
        "account_id" : 30184,
        "reputation" : 100604,
        "user_id" : 82156,
        "user_type" : "registered",
        "accept_rate" : 65,
        "profile_image" : "https://www.gravatar.com/avatar/5b800d2444930f6f465fb284647b5204?s=256&d=identicon&r=PG",
        "display_name" : "emmby",
        "link" : "https://stackoverflow.com/users/82156/emmby"
      },
      "edited" : false,
      "score" : 3,
      "creation_date" : 1308608373,
      "post_id" : 6393502,
      "comment_id" : 7529105,
      "content_license" : "CC BY-SA 3.0",
      "body" : "FYI Base64 is available in API level 8 (2.2) and later.  You can use <a href=\"http://iharder.sourceforge.net/current/java/base64/\" rel=\"nofollow noreferrer\">iharder.sourceforge.net/current/java/base64</a> or something else for earlier OSs."
    }, {
      "owner" : {
        "account_id" : 30184,
        "reputation" : 100604,
        "user_id" : 82156,
        "user_type" : "registered",
        "accept_rate" : 65,
        "profile_image" : "https://www.gravatar.com/avatar/5b800d2444930f6f465fb284647b5204?s=256&d=identicon&r=PG",
        "display_name" : "emmby",
        "link" : "https://stackoverflow.com/users/82156/emmby"
      },
      "edited" : false,
      "score" : 0,
      "creation_date" : 1309981497,
      "post_id" : 6393502,
      "comment_id" : 7790429,
      "content_license" : "CC BY-SA 3.0",
      "body" : "And another os version-related comment: some devices return null for ANDROID_ID on os 2.1 or earlier, so you&#39;ll want to use a known value in those situations.  Something like &quot;9774d56d682e549c&quot;, which is the android emulator id, might work."
    }, {
      "owner" : {
        "account_id" : 116622,
        "reputation" : 1083,
        "user_id" : 305736,
        "user_type" : "registered",
        "profile_image" : "https://www.gravatar.com/avatar/e3d10645136cc854b52caa4e3defc690?s=256&d=identicon&r=PG",
        "display_name" : "Matt Brian&#231;on",
        "link" : "https://stackoverflow.com/users/305736/matt-brian%c3%a7on"
      },
      "edited" : false,
      "score" : 1,
      "creation_date" : 1325978768,
      "post_id" : 6393502,
      "comment_id" : 10938246,
      "content_license" : "CC BY-SA 3.0",
      "body" : "Or generate your own ID: <a href=\"http://android-developers.blogspot.com/2011/03/identifying-app-installations.html\" rel=\"nofollow noreferrer\">android-developers.blogspot.com/2011/03/&hellip;</a>"
    }, {
      "owner" : {
        "account_id" : 39531,
        "reputation" : 190032,
        "user_id" : 114066,
        "user_type" : "registered",
        "accept_rate" : 90,
        "profile_image" : "https://i.sstatic.net/BpRie.jpg?s=256",
        "display_name" : "Janusz",
        "link" : "https://stackoverflow.com/users/114066/janusz"
      },
      "edited" : false,
      "score" : 2,
      "creation_date" : 1347280490,
      "post_id" : 6393502,
      "comment_id" : 16585238,
      "content_license" : "CC BY-SA 3.0",
      "body" : "@emmby Is this code that you have created? If yes is it okay to use it in a closed source app? If you want attribution for the code how do you want to be attributed?"
    }, {
      "owner" : {
        "account_id" : 30184,
        "reputation" : 100604,
        "user_id" : 82156,
        "user_type" : "registered",
        "accept_rate" : 65,
        "profile_image" : "https://www.gravatar.com/avatar/5b800d2444930f6f465fb284647b5204?s=256&d=identicon&r=PG",
        "display_name" : "emmby",
        "link" : "https://stackoverflow.com/users/82156/emmby"
      },
      "edited" : false,
      "score" : 39,
      "creation_date" : 1347294064,
      "post_id" : 6393502,
      "comment_id" : 16591485,
      "content_license" : "CC BY-SA 3.0",
      "body" : "Yes, I wrote this.  Feel free to use, no attribution necessary"
    }, {
      "owner" : {
        "account_id" : 232265,
        "reputation" : 7099,
        "user_id" : 496992,
        "user_type" : "registered",
        "accept_rate" : 80,
        "profile_image" : "https://www.gravatar.com/avatar/e2f115ff65f184658ec426c5c6b793db?s=256&d=identicon&r=PG",
        "display_name" : "Patrick Boos",
        "link" : "https://stackoverflow.com/users/496992/patrick-boos"
      },
      "edited" : false,
      "score" : 8,
      "creation_date" : 1348450994,
      "post_id" : 6393502,
      "comment_id" : 16914921,
      "content_license" : "CC BY-SA 3.0",
      "body" : "I agree with you. But if the password is only used on the server, why not use Public/private key encryption? Public key on client when saving the password. The client will never have to read the clear text password again, right? The server can then decrypt it with the private key. So even if somebody goes through your app source code, they can&#39;t get the password, except they hack your server and get the private key."
    }, {
      "owner" : {
        "account_id" : 934016,
        "reputation" : 1061,
        "user_id" : 963298,
        "user_type" : "registered",
        "accept_rate" : 76,
        "profile_image" : "https://i.sstatic.net/XKNUV.jpg?s=256",
        "display_name" : "stephen",
        "link" : "https://stackoverflow.com/users/963298/stephen"
      },
      "edited" : false,
      "score" : 0,
      "creation_date" : 1358377291,
      "post_id" : 6393502,
      "comment_id" : 19982616,
      "content_license" : "CC BY-SA 3.0",
      "body" : "Great contribution.  I&#39;d like to add that Android warns against inner classes having making reference to their creators (potential leak).  Try declaring Editor static, and create a WeakReference to the outer class to call encrypt/decrypt.  Also: require the constructor for Editor to take the outer class for assignment in constructor.  That should alleviate any concerns with leaks.  Although I am a Java newb...feel free to criticize."
    }, {
      "owner" : {
        "account_id" : 103956,
        "reputation" : 4461,
        "user_id" : 278174,
        "user_type" : "registered",
        "accept_rate" : 85,
        "profile_image" : "https://www.gravatar.com/avatar/17166f60f451a5bf7bf4ed8ab8e30fa4?s=256&d=identicon&r=PG&f=y&so-version=2",
        "display_name" : "powder366",
        "link" : "https://stackoverflow.com/users/278174/powder366"
      },
      "edited" : false,
      "score" : 1,
      "creation_date" : 1360867866,
      "post_id" : 6393502,
      "comment_id" : 20867012,
      "content_license" : "CC BY-SA 3.0",
      "body" : "Get: Caused by: javax.crypto.IllegalBlockSizeException: last block incomplete in decryption?"
    }, {
      "owner" : {
        "account_id" : 355923,
        "reputation" : 6898,
        "user_id" : 695134,
        "user_type" : "registered",
        "accept_rate" : 34,
        "profile_image" : "https://www.gravatar.com/avatar/98db04b16073eb8da1d437432452c355?s=256&d=identicon&r=PG",
        "display_name" : "Neil Walker",
        "link" : "https://stackoverflow.com/users/695134/neil-walker"
      },
      "edited" : false,
      "score" : 0,
      "creation_date" : 1363279751,
      "post_id" : 6393502,
      "comment_id" : 21796975,
      "content_license" : "CC BY-SA 3.0",
      "body" : "I&#39;m a bit confused. The first paragraph states not to encrypt password as access to the binary gives potential access to the key, yet the example answer is to encrypt the password using a key?"
    }, {
      "owner" : {
        "account_id" : 1080473,
        "reputation" : 10532,
        "user_id" : 1077601,
        "user_type" : "registered",
        "accept_rate" : 75,
        "profile_image" : "https://www.gravatar.com/avatar/8156916199f65a68c31dac5b8ad4151c?s=256&d=identicon&r=PG",
        "display_name" : "Darren",
        "link" : "https://stackoverflow.com/users/1077601/darren"
      },
      "edited" : false,
      "score" : 0,
      "creation_date" : 1365597582,
      "post_id" : 6393502,
      "comment_id" : 22686313,
      "content_license" : "CC BY-SA 3.0",
      "body" : "I&#39;ve just dumped this into my android project, but it complains that DEVICE_ID is deprecated. Is this still ok to use?"
    }, {
      "owner" : {
        "account_id" : 239116,
        "reputation" : 5254,
        "user_id" : 508479,
        "user_type" : "registered",
        "accept_rate" : 87,
        "profile_image" : "https://www.gravatar.com/avatar/ff5b025de8b6a87738bb67cf697297c4?s=256&d=identicon&r=PG",
        "display_name" : "dwbrito",
        "link" : "https://stackoverflow.com/users/508479/dwbrito"
      },
      "edited" : false,
      "score" : 2,
      "creation_date" : 1371552886,
      "post_id" : 6393502,
      "comment_id" : 24853748,
      "content_license" : "CC BY-SA 3.0",
      "body" : "You should use now Settings.Secure.ANDROID_ID, according to this: <a href=\"http://developer.android.com/reference/android/provider/Settings.System.html#ANDROID_ID\" rel=\"nofollow noreferrer\">developer.android.com/reference/android/provider/&hellip;</a>"
    }, {
      "owner" : {
        "account_id" : 2679825,
        "reputation" : 2615,
        "user_id" : 2315405,
        "user_type" : "registered",
        "accept_rate" : 84,
        "profile_image" : "https://i.sstatic.net/kq3iR.png?s=256",
        "display_name" : "D4rWiNS",
        "link" : "https://stackoverflow.com/users/2315405/d4rwins"
      },
      "edited" : false,
      "score" : 0,
      "creation_date" : 1396008071,
      "post_id" : 6393502,
      "comment_id" : 34609553,
      "content_license" : "CC BY-SA 3.0",
      "body" : "For that users that are starting and dont understand Settings.Secure.Android_ID just  change that line:  pbeCipher.init(Cipher.ENCRYPT_MODE, key, new PBEParameterSpec(Settings.Secure.getString(context.getConten&zwnj;&#8203;tResolver(),Settings&zwnj;&#8203;.System.ANDROID_ID).&zwnj;&#8203;getBytes(UTF8), 20));  for that one:  pbeCipher.init(Cipher.ENCRYPT_MODE, key, new PBEParameterSpec( Secure.getString(context.getContentResolver(), Secure.ANDROID_ID).getBytes(UTF8), 20));"
    }, {
      "owner" : {
        "account_id" : 363084,
        "reputation" : 1738,
        "user_id" : 1212832,
        "user_type" : "registered",
        "profile_image" : "https://www.gravatar.com/avatar/1eee06c83f56235ab6e236392c056be8?s=256&d=identicon&r=PG",
        "display_name" : "RightHandedMonkey",
        "link" : "https://stackoverflow.com/users/1212832/righthandedmonkey"
      },
      "edited" : false,
      "score" : 4,
      "creation_date" : 1398266130,
      "post_id" : 6393502,
      "comment_id" : 35573270,
      "content_license" : "CC BY-SA 3.0",
      "body" : "I&#39;ve added a few features to this code and placed it on github at <a href=\"https://github.com/RightHandedMonkey/WorxForUs_Library/blob/master/src/com/worxforus/android/ObscuredSharedPreferences.java\" rel=\"nofollow noreferrer\">github.com/RightHandedMonkey/WorxForUs_Library/blob/master/s&zwnj;&#8203;rc/&hellip;</a>.  It now handles migrating a non-encrypted preferences to the encrypted one.  Also it generates the key at runtime, so decompiling the app does not release the key."
    }, {
      "owner" : {
        "account_id" : 1477527,
        "reputation" : 8167,
        "user_id" : 1387588,
        "user_type" : "registered",
        "accept_rate" : 59,
        "profile_image" : "https://www.gravatar.com/avatar/63791bbcac8b8f1226eebe450306ca15?s=256&d=identicon&r=PG",
        "display_name" : "sports",
        "link" : "https://stackoverflow.com/users/1387588/sports"
      },
      "edited" : false,
      "score" : 0,
      "creation_date" : 1399395247,
      "post_id" : 6393502,
      "comment_id" : 36039888,
      "content_license" : "CC BY-SA 3.0",
      "body" : "I dont understand the logic in this implication: &quot;...have access to your application&#39;s binary, and therefore the keys to unencrypt the password.&quot;. How you explain here p --&gt; q ?"
    }, {
      "owner" : {
        "account_id" : 1761903,
        "reputation" : 10076,
        "user_id" : 1608786,
        "user_type" : "registered",
        "accept_rate" : 92,
        "profile_image" : "https://i.sstatic.net/3n7zh.jpg?s=256",
        "display_name" : "Derek W",
        "link" : "https://stackoverflow.com/users/1608786/derek-w"
      },
      "reply_to_user" : {
        "account_id" : 1477527,
        "reputation" : 8167,
        "user_id" : 1387588,
        "user_type" : "registered",
        "accept_rate" : 59,
        "profile_image" : "https://www.gravatar.com/avatar/63791bbcac8b8f1226eebe450306ca15?s=256&d=identicon&r=PG",
        "display_name" : "sports",
        "link" : "https://stackoverflow.com/users/1387588/sports"
      },
      "edited" : false,
      "score" : 0,
      "creation_date" : 1400686460,
      "post_id" : 6393502,
      "comment_id" : 36584923,
      "content_license" : "CC BY-SA 3.0",
      "body" : "@sports: Having the binaries means that they can decompile your app and then the keys stored in code are visible to the attacker. They can use these keys to unencrypt the password information."
    }, {
      "owner" : {
        "account_id" : 1477527,
        "reputation" : 8167,
        "user_id" : 1387588,
        "user_type" : "registered",
        "accept_rate" : 59,
        "profile_image" : "https://www.gravatar.com/avatar/63791bbcac8b8f1226eebe450306ca15?s=256&d=identicon&r=PG",
        "display_name" : "sports",
        "link" : "https://stackoverflow.com/users/1387588/sports"
      },
      "reply_to_user" : {
        "account_id" : 1761903,
        "reputation" : 10076,
        "user_id" : 1608786,
        "user_type" : "registered",
        "accept_rate" : 92,
        "profile_image" : "https://i.sstatic.net/3n7zh.jpg?s=256",
        "display_name" : "Derek W",
        "link" : "https://stackoverflow.com/users/1608786/derek-w"
      },
      "edited" : false,
      "score" : 0,
      "creation_date" : 1400697028,
      "post_id" : 6393502,
      "comment_id" : 36591414,
      "content_license" : "CC BY-SA 3.0",
      "body" : "@DerekW you make &quot;decompiling&quot; to look like it is a trivial, easy and even possible thing. Do you have a proof of this? ie: &quot;prove that given any binaries,  you can decompile sourcecode.&quot; ..so this means that I can decompile WhatsApp (and any other closedsource application) and check out the sourcecode? Or by decompiling I can only obtain hardcoded values used by the rest of teh code?"
    }, {
      "owner" : {
        "account_id" : 1761903,
        "reputation" : 10076,
        "user_id" : 1608786,
        "user_type" : "registered",
        "accept_rate" : 92,
        "profile_image" : "https://i.sstatic.net/3n7zh.jpg?s=256",
        "display_name" : "Derek W",
        "link" : "https://stackoverflow.com/users/1608786/derek-w"
      },
      "reply_to_user" : {
        "account_id" : 1477527,
        "reputation" : 8167,
        "user_id" : 1387588,
        "user_type" : "registered",
        "accept_rate" : 59,
        "profile_image" : "https://www.gravatar.com/avatar/63791bbcac8b8f1226eebe450306ca15?s=256&d=identicon&r=PG",
        "display_name" : "sports",
        "link" : "https://stackoverflow.com/users/1387588/sports"
      },
      "edited" : false,
      "score" : 1,
      "creation_date" : 1400701989,
      "post_id" : 6393502,
      "comment_id" : 36594171,
      "content_license" : "CC BY-SA 3.0",
      "body" : "@sports: Trivial is a relative term, but the best you can truly do is make the would-be hacker work for it. Here&#39;s a question that more fully addresses your question: <a href=\"http://stackoverflow.com/questions/13854425/how-to-avoid-reverse-engineering-of-an-apk-file\" title=\"how to avoid reverse engineering of an apk file\">stackoverflow.com/questions/13854425/&hellip;</a>"
    }, {
      "owner" : {
        "account_id" : 437303,
        "reputation" : 8245,
        "user_id" : 824914,
        "user_type" : "registered",
        "profile_image" : "https://www.gravatar.com/avatar/828089be2718bc732f2e188056a096b1?s=256&d=identicon&r=PG",
        "display_name" : "David Olsson",
        "link" : "https://stackoverflow.com/users/824914/david-olsson"
      },
      "edited" : false,
      "score" : 0,
      "creation_date" : 1408281113,
      "post_id" : 6393502,
      "comment_id" : 39522424,
      "content_license" : "CC BY-SA 3.0",
      "body" : "Bump I guess. But with this implementation against sdk19 I get a thrown exception (InvalidAlgorithmParameterException) when encrypting."
    }, {
      "owner" : {
        "account_id" : 1078213,
        "reputation" : 1112,
        "user_id" : 1075909,
        "user_type" : "registered",
        "accept_rate" : 43,
        "profile_image" : "https://www.gravatar.com/avatar/ec0ac4cb6f68540ae1fd42d47d408e2f?s=256&d=identicon&r=PG",
        "display_name" : "adevine",
        "link" : "https://stackoverflow.com/users/1075909/adevine"
      },
      "reply_to_user" : {
        "account_id" : 232265,
        "reputation" : 7099,
        "user_id" : 496992,
        "user_type" : "registered",
        "accept_rate" : 80,
        "profile_image" : "https://www.gravatar.com/avatar/e2f115ff65f184658ec426c5c6b793db?s=256&d=identicon&r=PG",
        "display_name" : "Patrick Boos",
        "link" : "https://stackoverflow.com/users/496992/patrick-boos"
      },
      "edited" : false,
      "score" : 3,
      "creation_date" : 1414101329,
      "post_id" : 6393502,
      "comment_id" : 41701858,
      "content_license" : "CC BY-SA 3.0",
      "body" : "Late addition, but the comment by @PatrickBoos is a great idea. One problem with this, though, is that even though you&#39;ve encrypted the password, an attacker that stole that cipher would still be able to log in to your servers, because your servers do the decryption. One addition to this approach is to encrypt the password together with a timestamp. That way you can decide, for example, to only allow passwords saved in the recent past (like adding an expiration date to your &quot;token&quot;), or even requiring certain users to have a timestamp since a particular date (let&#39;s you &quot;revoke&quot; old &quot;tokens&quot;)."
    }, {
      "owner" : {
        "account_id" : 1544480,
        "reputation" : 36563,
        "user_id" : 1438339,
        "user_type" : "registered",
        "accept_rate" : 75,
        "profile_image" : "https://i.sstatic.net/eJSFM.jpg?s=256",
        "display_name" : "Adam Johns",
        "link" : "https://stackoverflow.com/users/1438339/adam-johns"
      },
      "edited" : false,
      "score" : 0,
      "creation_date" : 1414638857,
      "post_id" : 6393502,
      "comment_id" : 41894968,
      "content_license" : "CC BY-SA 3.0",
      "body" : "FYI as of Android 4.0.1, there are a couple of new methods on SharedPreferences you need to override"
    }, {
      "owner" : {
        "account_id" : 1155287,
        "reputation" : 1062,
        "user_id" : 1136074,
        "user_type" : "registered",
        "accept_rate" : 60,
        "profile_image" : "https://i.sstatic.net/c07my.jpg?s=256",
        "display_name" : "gor",
        "link" : "https://stackoverflow.com/users/1136074/gor"
      },
      "edited" : false,
      "score" : 0,
      "creation_date" : 1452995047,
      "post_id" : 6393502,
      "comment_id" : 57409848,
      "content_license" : "CC BY-SA 3.0",
      "body" : "for a certain attack vector, a simple reverse engineering would do the trick and get your decryption key."
    }, {
      "owner" : {
        "account_id" : 3045053,
        "reputation" : 11948,
        "user_id" : 2580975,
        "user_type" : "registered",
        "accept_rate" : 71,
        "profile_image" : "https://www.gravatar.com/avatar/b7239dc52f0e85c0d7cc5c72b9cfa4dd?s=256&d=identicon&r=PG&f=y&so-version=2",
        "display_name" : "Shayan Pourvatan",
        "link" : "https://stackoverflow.com/users/2580975/shayan-pourvatan"
      },
      "edited" : false,
      "score" : 0,
      "creation_date" : 1455693194,
      "post_id" : 6393502,
      "comment_id" : 58597271,
      "content_license" : "CC BY-SA 3.0",
      "body" : "Hi @emmby, thanks for great answer, i&#39;ve used your code in my application, but i&#39;ve got following error in decrypt method ( javax.crypto.BadPaddingException: pad block corrupted). I searched error but i don&#39;t find any solution. can you help me on this error ? i don&#39;t get this error all time, 3 user crash from 3k."
    }, {
      "owner" : {
        "account_id" : 3158057,
        "reputation" : 2347,
        "user_id" : 2669960,
        "user_type" : "registered",
        "accept_rate" : 83,
        "profile_image" : "https://i.sstatic.net/W74fC.jpg?s=256",
        "display_name" : "Kevin Lee",
        "link" : "https://stackoverflow.com/users/2669960/kevin-lee"
      },
      "edited" : false,
      "score" : 0,
      "creation_date" : 1458364314,
      "post_id" : 6393502,
      "comment_id" : 59840023,
      "content_license" : "CC BY-SA 3.0",
      "body" : "Regarding the password problem, &quot;encrypting&quot; sharedprefs isn&#39;t the solution, a better way is to store a hash of a salted password instead, so that the original password cannot be guessed if it&#39;s compromised (good given that many people reuse their passwords). It&#39;s good that publicity is shed on these issues and there are already best practices out there beyond the scope of this question to manage credentials on any system."
    }, {
      "owner" : {
        "account_id" : 2970960,
        "reputation" : 1859,
        "user_id" : 2523007,
        "user_type" : "registered",
        "accept_rate" : 55,
        "profile_image" : "https://i.sstatic.net/aCsFp.jpg?s=256",
        "display_name" : "vanomart",
        "link" : "https://stackoverflow.com/users/2523007/vanomart"
      },
      "edited" : false,
      "score" : 0,
      "creation_date" : 1462012483,
      "post_id" : 6393502,
      "comment_id" : 61465378,
      "content_license" : "CC BY-SA 3.0",
      "body" : "what is the most secure way to set SEKRIT field - compile time, from some user input or totally randomly generate at install time and then somehow store it in the preferences for future use?"
    } ],
    "owner" : {
      "account_id" : 30184,
      "reputation" : 100604,
      "user_id" : 82156,
      "user_type" : "registered",
      "accept_rate" : 65,
      "profile_image" : "https://www.gravatar.com/avatar/5b800d2444930f6f465fb284647b5204?s=256&d=identicon&r=PG",
      "display_name" : "emmby",
      "link" : "https://stackoverflow.com/users/82156/emmby"
    },
    "is_accepted" : false,
    "score" : 213,
    "last_activity_date" : 1460567354,
    "last_edit_date" : 1460567354,
    "creation_date" : 1308364929,
    "answer_id" : 6393502,
    "question_id" : 785973,
    "content_license" : "CC BY-SA 3.0",
    "body" : "<p>I agree with Reto and fiXedd.  Objectively speaking it doesn't make a lot of sense investing significant time and effort into encrypting passwords in SharedPreferences since any attacker that has access to your preferences file is fairly likely to also have access to your application's binary, and therefore the keys to unencrypt the password.</p>\n\n<p>However, that being said, there does seem to be a publicity initiative going on identifying mobile applications that store their passwords in cleartext in SharedPreferences and shining unfavorable light on those applications.  See <a href=\"http://blogs.wsj.com/digits/2011/06/08/some-top-apps-put-data-at-risk/\" rel=\"noreferrer\">http://blogs.wsj.com/digits/2011/06/08/some-top-apps-put-data-at-risk/</a> and <a href=\"http://viaforensics.com/appwatchdog\" rel=\"noreferrer\">http://viaforensics.com/appwatchdog</a> for some examples.  </p>\n\n<p>While we need more attention paid to security in general, I would argue that this sort of attention on this one particular issue doesn't actually significantly increase our overall security.  However, perceptions being as they are, here's a solution to encrypt the data you place in SharedPreferences.</p>\n\n<p>Simply wrap your own SharedPreferences object in this one, and any data you read/write will be automatically encrypted and decrypted.  eg.</p>\n\n<pre><code>final SharedPreferences prefs = new ObscuredSharedPreferences( \n    this, this.getSharedPreferences(MY_PREFS_FILE_NAME, Context.MODE_PRIVATE) );\n\n// eg.    \nprefs.edit().putString(\"foo\",\"bar\").commit();\nprefs.getString(\"foo\", null);\n</code></pre>\n\n<p>Here's the code for the class:</p>\n\n<pre><code>/**\n * Warning, this gives a false sense of security.  If an attacker has enough access to\n * acquire your password store, then he almost certainly has enough access to acquire your\n * source binary and figure out your encryption key.  However, it will prevent casual\n * investigators from acquiring passwords, and thereby may prevent undesired negative\n * publicity.\n */\npublic class ObscuredSharedPreferences implements SharedPreferences {\n    protected static final String UTF8 = \"utf-8\";\n    private static final char[] SEKRIT = ... ; // INSERT A RANDOM PASSWORD HERE.\n                                               // Don't use anything you wouldn't want to\n                                               // get out there if someone decompiled\n                                               // your app.\n\n\n    protected SharedPreferences delegate;\n    protected Context context;\n\n    public ObscuredSharedPreferences(Context context, SharedPreferences delegate) {\n        this.delegate = delegate;\n        this.context = context;\n    }\n\n    public class Editor implements SharedPreferences.Editor {\n        protected SharedPreferences.Editor delegate;\n\n        public Editor() {\n            this.delegate = ObscuredSharedPreferences.this.delegate.edit();                    \n        }\n\n        @Override\n        public Editor putBoolean(String key, boolean value) {\n            delegate.putString(key, encrypt(Boolean.toString(value)));\n            return this;\n        }\n\n        @Override\n        public Editor putFloat(String key, float value) {\n            delegate.putString(key, encrypt(Float.toString(value)));\n            return this;\n        }\n\n        @Override\n        public Editor putInt(String key, int value) {\n            delegate.putString(key, encrypt(Integer.toString(value)));\n            return this;\n        }\n\n        @Override\n        public Editor putLong(String key, long value) {\n            delegate.putString(key, encrypt(Long.toString(value)));\n            return this;\n        }\n\n        @Override\n        public Editor putString(String key, String value) {\n            delegate.putString(key, encrypt(value));\n            return this;\n        }\n\n        @Override\n        public void apply() {\n            delegate.apply();\n        }\n\n        @Override\n        public Editor clear() {\n            delegate.clear();\n            return this;\n        }\n\n        @Override\n        public boolean commit() {\n            return delegate.commit();\n        }\n\n        @Override\n        public Editor remove(String s) {\n            delegate.remove(s);\n            return this;\n        }\n    }\n\n    public Editor edit() {\n        return new Editor();\n    }\n\n\n    @Override\n    public Map&lt;String, ?&gt; getAll() {\n        throw new UnsupportedOperationException(); // left as an exercise to the reader\n    }\n\n    @Override\n    public boolean getBoolean(String key, boolean defValue) {\n        final String v = delegate.getString(key, null);\n        return v!=null ? Boolean.parseBoolean(decrypt(v)) : defValue;\n    }\n\n    @Override\n    public float getFloat(String key, float defValue) {\n        final String v = delegate.getString(key, null);\n        return v!=null ? Float.parseFloat(decrypt(v)) : defValue;\n    }\n\n    @Override\n    public int getInt(String key, int defValue) {\n        final String v = delegate.getString(key, null);\n        return v!=null ? Integer.parseInt(decrypt(v)) : defValue;\n    }\n\n    @Override\n    public long getLong(String key, long defValue) {\n        final String v = delegate.getString(key, null);\n        return v!=null ? Long.parseLong(decrypt(v)) : defValue;\n    }\n\n    @Override\n    public String getString(String key, String defValue) {\n        final String v = delegate.getString(key, null);\n        return v != null ? decrypt(v) : defValue;\n    }\n\n    @Override\n    public boolean contains(String s) {\n        return delegate.contains(s);\n    }\n\n    @Override\n    public void registerOnSharedPreferenceChangeListener(OnSharedPreferenceChangeListener onSharedPreferenceChangeListener) {\n        delegate.registerOnSharedPreferenceChangeListener(onSharedPreferenceChangeListener);\n    }\n\n    @Override\n    public void unregisterOnSharedPreferenceChangeListener(OnSharedPreferenceChangeListener onSharedPreferenceChangeListener) {\n        delegate.unregisterOnSharedPreferenceChangeListener(onSharedPreferenceChangeListener);\n    }\n\n\n\n\n    protected String encrypt( String value ) {\n\n        try {\n            final byte[] bytes = value!=null ? value.getBytes(UTF8) : new byte[0];\n            SecretKeyFactory keyFactory = SecretKeyFactory.getInstance(\"PBEWithMD5AndDES\");\n            SecretKey key = keyFactory.generateSecret(new PBEKeySpec(SEKRIT));\n            Cipher pbeCipher = Cipher.getInstance(\"PBEWithMD5AndDES\");\n            pbeCipher.init(Cipher.ENCRYPT_MODE, key, new PBEParameterSpec(Settings.Secure.getString(context.getContentResolver(),Settings.Secure.ANDROID_ID).getBytes(UTF8), 20));\n            return new String(Base64.encode(pbeCipher.doFinal(bytes), Base64.NO_WRAP),UTF8);\n\n        } catch( Exception e ) {\n            throw new RuntimeException(e);\n        }\n\n    }\n\n    protected String decrypt(String value){\n        try {\n            final byte[] bytes = value!=null ? Base64.decode(value,Base64.DEFAULT) : new byte[0];\n            SecretKeyFactory keyFactory = SecretKeyFactory.getInstance(\"PBEWithMD5AndDES\");\n            SecretKey key = keyFactory.generateSecret(new PBEKeySpec(SEKRIT));\n            Cipher pbeCipher = Cipher.getInstance(\"PBEWithMD5AndDES\");\n            pbeCipher.init(Cipher.DECRYPT_MODE, key, new PBEParameterSpec(Settings.Secure.getString(context.getContentResolver(),Settings.Secure.ANDROID_ID).getBytes(UTF8), 20));\n            return new String(pbeCipher.doFinal(bytes),UTF8);\n\n        } catch( Exception e) {\n            throw new RuntimeException(e);\n        }\n    }\n\n}\n</code></pre>\n"
  }, {
    "comments" : [ {
      "owner" : {
        "account_id" : 1618,
        "reputation" : 74837,
        "user_id" : 2172,
        "user_type" : "registered",
        "accept_rate" : 86,
        "profile_image" : "https://www.gravatar.com/avatar/d45a34439ae17a079045a23df5131b91?s=256&d=identicon&r=PG",
        "display_name" : "Sander Versluys",
        "link" : "https://stackoverflow.com/users/2172/sander-versluys"
      },
      "edited" : false,
      "score" : 2,
      "creation_date" : 1352369685,
      "post_id" : 10016789,
      "comment_id" : 18115323,
      "content_license" : "CC BY-SA 3.0",
      "body" : "Please note that using the AccountManager is not more secure than any other method provided above! <a href=\"http://developer.android.com/training/id-auth/custom_auth.html#Security\" rel=\"nofollow noreferrer\">developer.android.com/training/id-auth/&hellip;</a>"
    }, {
      "owner" : {
        "account_id" : 129490,
        "reputation" : 8890,
        "user_id" : 328115,
        "user_type" : "registered",
        "accept_rate" : 44,
        "profile_image" : "https://www.gravatar.com/avatar/9a029d2d948f128443f996fa12b3d3a1?s=256&d=identicon&r=PG",
        "display_name" : "dolmen",
        "link" : "https://stackoverflow.com/users/328115/dolmen"
      },
      "edited" : false,
      "score" : 1,
      "creation_date" : 1352680458,
      "post_id" : 10016789,
      "comment_id" : 18198950,
      "content_license" : "CC BY-SA 3.0",
      "body" : "The use case for AccountManager is when the account has to be shared between different apps, and apps from different authors. Storing the password and giving it to any requesting app would not be appropriate. If the usage of the user/password is only for a single app, don&#39;t use AccountManager."
    }, {
      "owner" : {
        "account_id" : 189654,
        "reputation" : 6591,
        "user_id" : 429108,
        "user_type" : "registered",
        "accept_rate" : 80,
        "profile_image" : "https://www.gravatar.com/avatar/eccf7c340d29d7994b5427fe481c6e34?s=256&d=identicon&r=PG",
        "display_name" : "Jon O",
        "link" : "https://stackoverflow.com/users/429108/jon-o"
      },
      "reply_to_user" : {
        "account_id" : 129490,
        "reputation" : 8890,
        "user_id" : 328115,
        "user_type" : "registered",
        "accept_rate" : 44,
        "profile_image" : "https://www.gravatar.com/avatar/9a029d2d948f128443f996fa12b3d3a1?s=256&d=identicon&r=PG",
        "display_name" : "dolmen",
        "link" : "https://stackoverflow.com/users/328115/dolmen"
      },
      "edited" : false,
      "score" : 1,
      "creation_date" : 1352734656,
      "post_id" : 10016789,
      "comment_id" : 18214455,
      "content_license" : "CC BY-SA 3.0",
      "body" : "@dolmen, that&#39;s not quite correct.  The AccountManager won&#39;t give the account password to any app whose UID doesn&#39;t match the Authenticator&#39;s.  The name, yes; the auth token, yes; the password, no.  If you try, it&#39;ll throw a SecurityException.  And the use case is much broader than that.  <a href=\"http://developer.android.com/training/id-auth/identify.html\" rel=\"nofollow noreferrer\">developer.android.com/training/id-auth/identify.html</a>"
    } ],
    "owner" : {
      "account_id" : 189654,
      "reputation" : 6591,
      "user_id" : 429108,
      "user_type" : "registered",
      "accept_rate" : 80,
      "profile_image" : "https://www.gravatar.com/avatar/eccf7c340d29d7994b5427fe481c6e34?s=256&d=identicon&r=PG",
      "display_name" : "Jon O",
      "link" : "https://stackoverflow.com/users/429108/jon-o"
    },
    "is_accepted" : false,
    "score" : 5,
    "last_activity_date" : 1333562680,
    "creation_date" : 1333562680,
    "answer_id" : 10016789,
    "question_id" : 785973,
    "content_license" : "CC BY-SA 3.0",
    "body" : "<p>I know this is a little bit of necromancy, but you should use the Android <a href=\"http://developer.android.com/reference/android/accounts/AccountManager.html\" rel=\"noreferrer\">AccountManager</a>.  It's purpose-built for this scenario.  It's a little bit cumbersome but one of the things it does is invalidate the local credentials if the SIM card changes, so if somebody swipes your phone and throws a new SIM in it, your credentials won't be compromised.</p>\n\n<p>This also gives the user a quick and easy way to access (and potentially delete) the stored credentials for any account they have on the device, all from one place.</p>\n\n<p><a href=\"http://developer.android.com/resources/samples/SampleSyncAdapter/index.html\" rel=\"noreferrer\">SampleSyncAdapter</a> is an example that makes use of stored account credentials.</p>\n"
  }, {
    "owner" : {
      "account_id" : 1654265,
      "reputation" : 6378,
      "user_id" : 1524209,
      "user_type" : "registered",
      "profile_image" : "https://www.gravatar.com/avatar/f090818aac804ea2feb1966095b29665?s=256&d=identicon&r=PG",
      "display_name" : "Joe Plante",
      "link" : "https://stackoverflow.com/users/1524209/joe-plante"
    },
    "is_accepted" : false,
    "score" : 6,
    "last_activity_date" : 1368538250,
    "last_edit_date" : 1368538250,
    "creation_date" : 1368537713,
    "answer_id" : 16544390,
    "question_id" : 785973,
    "content_license" : "CC BY-SA 3.0",
    "body" : "<p>Okay; it's been a while since the answer is kind-of mixed, but here's a few common answers. I researched this like crazy and it was hard to build a good answer</p>\n\n<ol>\n<li><p>The MODE_PRIVATE method is considered generally safe, if you assume that the user didn't root the device. Your data is stored in plain text in a part of the file system that can only be accessed by the original program. This makings grabbing the password with another app on a rooted device easy. Then again, do you want to support rooted devices?</p></li>\n<li><p>AES is still the best encryption you can do. Remember to look this up if you are starting a new implementation if it's been a while since I posted this. The largest issue with this is \"What to do with the encryption key?\"</p></li>\n</ol>\n\n<p>So, now we are at the \"What to do with the key?\" portion. This is the hard part. Getting the key turns out to be not that bad. You can use a key derivation function to take some password and make it a pretty secure key. You do get into issues like \"how many passes do you do with PKFDF2?\", but that's another topic</p>\n\n<ol>\n<li><p>Ideally, you store the AES key off the device. You have to figure out a good way to retrieve the key from the server safely, reliably, and securely though</p></li>\n<li><p>You have a login sequence of some sort (even the original login sequence you do for remote access). You can do two runs of your key generator on the same password. How this works is that you derive the key twice with a new salt and a new secure initialization vector. You store one of those generated passwords on the device, and you use the second password as the AES key.</p></li>\n</ol>\n\n<p>When you log in, you re-derive the key on the local login and compare it to the stored key. Once that is done, you use derive key #2 for AES.</p>\n\n<ol>\n<li>Using the \"generally safe\" approach, you encrypt the data using AES and store the key in MODE_PRIVATE. This is recommended by a recent-ish Android blog post. Not incredibly secure, but way better for some people over plain text</li>\n</ol>\n\n<p>You can do a lot of variations of these. For example, instead of a full login sequence, you can do a quick PIN (derived). The quick PIN might not be as secure as a full login sequence, but it's many times more secure than plain text</p>\n"
  }, {
    "owner" : {
      "account_id" : 92694,
      "reputation" : 11726,
      "user_id" : 253938,
      "user_type" : "registered",
      "accept_rate" : 81,
      "profile_image" : "https://www.gravatar.com/avatar/f56facf7921f4e2fbc9a38ca609cbf6b?s=256&d=identicon&r=PG",
      "display_name" : "RenniePet",
      "link" : "https://stackoverflow.com/users/253938/renniepet"
    },
    "is_accepted" : false,
    "score" : 1,
    "last_activity_date" : 1378446550,
    "creation_date" : 1378446550,
    "answer_id" : 18650766,
    "question_id" : 785973,
    "content_license" : "CC BY-SA 3.0",
    "body" : "<p>This answer is based on a suggested approach by Mark. A custom version of the EditTextPreference class is created which converts back and forth between the plain text seen in the view and an encrypted version of the password stored in the preferences storage. </p>\n\n<p>As has been pointed out by most who have answered on this thread, this is not a very secure technique, although the degree of security depends partly on the encryption/decryption code used. But it's fairly simple and convenient, and will thwart most casual snooping. </p>\n\n<p>Here is the code for the custom EditTextPreference class:</p>\n\n<pre><code>package com.Merlinia.OutBack_Client;\n\nimport android.content.Context;\nimport android.preference.EditTextPreference;\nimport android.util.AttributeSet;\nimport android.util.Base64;\n\nimport com.Merlinia.MEncryption_Main.MEncryptionUserPassword;\n\n\n/**\n * This class extends the EditTextPreference view, providing encryption and decryption services for\n * OutBack user passwords. The passwords in the preferences store are first encrypted using the\n * MEncryption classes and then converted to string using Base64 since the preferences store can not\n * store byte arrays.\n *\n * This is largely copied from this article, except for the encryption/decryption parts:\n * https://groups.google.com/forum/#!topic/android-developers/pMYNEVXMa6M\n */\npublic class EditPasswordPreference  extends EditTextPreference {\n\n    // Constructor - needed despite what compiler says, otherwise app crashes\n    public EditPasswordPreference(Context context) {\n        super(context);\n    }\n\n\n    // Constructor - needed despite what compiler says, otherwise app crashes\n    public EditPasswordPreference(Context context, AttributeSet attributeSet) {\n        super(context, attributeSet);\n    }\n\n\n    // Constructor - needed despite what compiler says, otherwise app crashes\n    public EditPasswordPreference(Context context, AttributeSet attributeSet, int defaultStyle) {\n        super(context, attributeSet, defaultStyle);\n    }\n\n\n    /**\n     * Override the method that gets a preference from the preferences storage, for display by the\n     * EditText view. This gets the base64 password, converts it to a byte array, and then decrypts\n     * it so it can be displayed in plain text.\n     * @return  OutBack user password in plain text\n     */\n    @Override\n    public String getText() {\n        String decryptedPassword;\n\n        try {\n            decryptedPassword = MEncryptionUserPassword.aesDecrypt(\n                     Base64.decode(getSharedPreferences().getString(getKey(), \"\"), Base64.DEFAULT));\n        } catch (Exception e) {\n            e.printStackTrace();\n            decryptedPassword = \"\";\n        }\n\n        return decryptedPassword;\n    }\n\n\n    /**\n     * Override the method that gets a text string from the EditText view and stores the value in\n     * the preferences storage. This encrypts the password into a byte array and then encodes that\n     * in base64 format.\n     * @param passwordText  OutBack user password in plain text\n     */\n    @Override\n    public void setText(String passwordText) {\n        byte[] encryptedPassword;\n\n        try {\n            encryptedPassword = MEncryptionUserPassword.aesEncrypt(passwordText);\n        } catch (Exception e) {\n            e.printStackTrace();\n            encryptedPassword = new byte[0];\n        }\n\n        getSharedPreferences().edit().putString(getKey(),\n                                          Base64.encodeToString(encryptedPassword, Base64.DEFAULT))\n                .commit();\n    }\n\n\n    @Override\n    protected void onSetInitialValue(boolean restoreValue, Object defaultValue) {\n        if (restoreValue)\n            getEditText().setText(getText());\n        else\n            super.onSetInitialValue(restoreValue, defaultValue);\n    }\n}\n</code></pre>\n\n<p>This shows how it can be used - this is the \"items\" file that drives the preferences display. Note it contains three ordinary EditTextPreference views and one of the custom EditPasswordPreference views.</p>\n\n<pre><code>&lt;PreferenceScreen xmlns:android=\"http://schemas.android.com/apk/res/android\"&gt;\n\n    &lt;EditTextPreference\n        android:key=\"@string/useraccountname_key\"\n        android:title=\"@string/useraccountname_title\"\n        android:summary=\"@string/useraccountname_summary\"\n        android:defaultValue=\"@string/useraccountname_default\"\n        /&gt;\n\n    &lt;com.Merlinia.OutBack_Client.EditPasswordPreference\n        android:key=\"@string/useraccountpassword_key\"\n        android:title=\"@string/useraccountpassword_title\"\n        android:summary=\"@string/useraccountpassword_summary\"\n        android:defaultValue=\"@string/useraccountpassword_default\"\n        /&gt;\n\n    &lt;EditTextPreference\n        android:key=\"@string/outbackserverip_key\"\n        android:title=\"@string/outbackserverip_title\"\n        android:summary=\"@string/outbackserverip_summary\"\n        android:defaultValue=\"@string/outbackserverip_default\"\n        /&gt;\n\n    &lt;EditTextPreference\n        android:key=\"@string/outbackserverport_key\"\n        android:title=\"@string/outbackserverport_title\"\n        android:summary=\"@string/outbackserverport_summary\"\n        android:defaultValue=\"@string/outbackserverport_default\"\n        /&gt;\n\n&lt;/PreferenceScreen&gt;\n</code></pre>\n\n<p>As for the actual encryption/decryption, that is left as an exercise for the reader. I'm currently using some code based on this article <a href=\"http://zenu.wordpress.com/2011/09/21/aes-128bit-cross-platform-java-and-c-encryption-compatibility/\" rel=\"nofollow\">http://zenu.wordpress.com/2011/09/21/aes-128bit-cross-platform-java-and-c-encryption-compatibility/</a>, although with different values for the key and the initialization vector.</p>\n"
  }, {
    "owner" : {
      "account_id" : 296946,
      "reputation" : 961,
      "user_id" : 602198,
      "user_type" : "registered",
      "profile_image" : "https://www.gravatar.com/avatar/d659fe0efab88f0be857a296b501032a?s=256&d=identicon&r=PG",
      "display_name" : "Marcell",
      "link" : "https://stackoverflow.com/users/602198/marcell"
    },
    "is_accepted" : false,
    "score" : 2,
    "last_activity_date" : 1379800300,
    "creation_date" : 1379800300,
    "answer_id" : 18938048,
    "question_id" : 785973,
    "content_license" : "CC BY-SA 3.0",
    "body" : "<p>You can also check out this little lib, containing the functionality you mention.</p>\n\n<p><a href=\"https://github.com/kovmarci86/android-secure-preferences\" rel=\"nofollow\">https://github.com/kovmarci86/android-secure-preferences</a></p>\n\n<p>It is similar to some of the other aproaches here. Hope helps :)</p>\n"
  }, {
    "owner" : {
      "account_id" : 3279331,
      "reputation" : 229,
      "user_id" : 2760300,
      "user_type" : "registered",
      "profile_image" : "https://www.gravatar.com/avatar/d619b7dc0628826143e43e9becdb3931?s=256&d=identicon&r=PG&f=y&so-version=2",
      "display_name" : "Rohit Jain",
      "link" : "https://stackoverflow.com/users/2760300/rohit-jain"
    },
    "is_accepted" : false,
    "score" : -3,
    "last_activity_date" : 1382085665,
    "creation_date" : 1382085665,
    "answer_id" : 19445205,
    "question_id" : 785973,
    "content_license" : "CC BY-SA 3.0",
    "body" : "<p>shared preferences is easiest way to store our application data. but it is possible that anyone can clear our shared preferences data through application manager.so i don't think it is completely safe for our application.  </p>\n"
  }, {
    "owner" : {
      "account_id" : 1170482,
      "reputation" : 1746,
      "user_id" : 1147787,
      "user_type" : "registered",
      "accept_rate" : 87,
      "profile_image" : "https://www.gravatar.com/avatar/489479d4c6d6f401c41e5ff3d9297923?s=256&d=identicon&r=PG",
      "display_name" : "Gauraw Yadav",
      "link" : "https://stackoverflow.com/users/1147787/gauraw-yadav"
    },
    "is_accepted" : false,
    "score" : 1,
    "last_activity_date" : 1386067256,
    "creation_date" : 1386067256,
    "answer_id" : 20348855,
    "question_id" : 785973,
    "content_license" : "CC BY-SA 3.0",
    "body" : "<p>First of all I think User's data shouldn't be stored on phone, and if it is must to store data somewhere on the phone it should be encrypted with in the apps private data. Security of users credentials should be the priority of the application.</p>\n\n<p>The sensitive data should be stored securely or not at all. In the event of a lost device or malware infection, data stored insecurely can be compromised.</p>\n"
  }, {
    "owner" : {
      "account_id" : 2149933,
      "reputation" : 53,
      "user_id" : 1906624,
      "user_type" : "registered",
      "profile_image" : "https://www.gravatar.com/avatar/3a1f41a878ed794a45cd21f373a8473d?s=256&d=identicon&r=PG",
      "display_name" : "dcgregorya",
      "link" : "https://stackoverflow.com/users/1906624/dcgregorya"
    },
    "is_accepted" : false,
    "score" : 5,
    "last_activity_date" : 1414688400,
    "creation_date" : 1414688400,
    "answer_id" : 26659028,
    "question_id" : 785973,
    "content_license" : "CC BY-SA 3.0",
    "body" : "<p>I'll throw my hat into the ring just to talk about securing passwords in general on Android.  On Android, the device binary should be considered compromised - this is the same for any end application which is in direct user control.  Conceptually, a hacker could use the necessary access to the binary to decompile it and root out your encrypted passwords and etc.</p>\n\n<p>As such there's two suggestions I'd like to throw out there if security is a major concern for you:</p>\n\n<p>1) Don't store the actual password.  Store a granted access token and use the access token and the signature of the phone to authenticate the session server-side.  The benefit to this is that you can make the token have a limited duration, you're not compromising the original password and you have a good signature that you can use to correlate to traffic later (to for instance check for intrusion attempts and invalidate the token rendering it useless).</p>\n\n<p>2) Utilize 2 factor authentication.  This may be more annoying and intrusive but for some compliance situations unavoidable.</p>\n"
  }, {
    "owner" : {
      "account_id" : 4531600,
      "reputation" : 516276,
      "user_id" : 3681880,
      "user_type" : "registered",
      "accept_rate" : 90,
      "profile_image" : "https://www.gravatar.com/avatar/3b7ad8915f552cd4e23caf38eee10030?s=256&d=identicon&r=PG",
      "display_name" : "Suragch",
      "link" : "https://stackoverflow.com/users/3681880/suragch"
    },
    "is_accepted" : false,
    "score" : 5,
    "last_activity_date" : 1508912663,
    "last_edit_date" : 1592644375,
    "creation_date" : 1508898771,
    "answer_id" : 46923005,
    "question_id" : 785973,
    "content_license" : "CC BY-SA 4.0",
    "body" : "<p><em>This is a supplemental answer for those arriving here based on the question title (like I did) and don't need to deal with the security issues related to saving passwords.</em></p>\n<h1>How to use Shared Preferences</h1>\n<p>User settings are generally saved locally in Android using <code>SharedPreferences</code> with a key-value pair. You use the <code>String</code> key to save or look up the associated value.</p>\n<h3>Write to Shared Preferences</h3>\n<pre><code>String key = &quot;myInt&quot;;\nint valueToSave = 10;\n\nSharedPreferences sharedPref = PreferenceManager.getDefaultSharedPreferences(context);\nSharedPreferences.Editor editor = sharedPref.edit();\neditor.putInt(key, valueToSave).commit();\n</code></pre>\n<p>Use <code>apply()</code> instead of <code>commit()</code> to save in the background rather than immediately.</p>\n<h3>Read from Shared Preferences</h3>\n<pre><code>String key = &quot;myInt&quot;;\nint defaultValue = 0;\n\nSharedPreferences sharedPref = PreferenceManager.getDefaultSharedPreferences(context);\nint savedValue = sharedPref.getInt(key, defaultValue);\n</code></pre>\n<p>The default value is used if the key isn't found.</p>\n<h1>Notes</h1>\n<ul>\n<li><p>Rather than using a local key String in multiple places like I did above, it would be better to use a constant in a single location. You could use something like this at the top of your settings activity:</p>\n<pre><code>  final static String PREF_MY_INT_KEY = &quot;myInt&quot;;\n</code></pre>\n</li>\n<li><p>I used an <code>int</code> in my example, but you can also use <code>putString()</code>, <code>putBoolean()</code>, <code>getString()</code>, <code>getBoolean()</code>, etc.</p>\n</li>\n<li><p>See the <a href=\"https://developer.android.com/training/basics/data-storage/shared-preferences.html\" rel=\"nofollow noreferrer\">documentation</a> for more details.</p>\n</li>\n<li><p>There are multiple ways to get SharedPreferences. See <a href=\"https://stackoverflow.com/a/46925053/3681880\">this answer</a> for what to look out for.</p>\n</li>\n</ul>\n"
  }, {
    "owner" : {
      "account_id" : 14428689,
      "reputation" : 11,
      "user_id" : 10422647,
      "user_type" : "registered",
      "profile_image" : "https://www.gravatar.com/avatar/8b3dd8c3e4278c91d3f34bc39fe01310?s=256&d=identicon&r=PG&f=y&so-version=2",
      "display_name" : "Braveblacklion",
      "link" : "https://stackoverflow.com/users/10422647/braveblacklion"
    },
    "is_accepted" : false,
    "score" : 1,
    "last_activity_date" : 1541597001,
    "creation_date" : 1541597001,
    "answer_id" : 53190347,
    "question_id" : 785973,
    "content_license" : "CC BY-SA 4.0",
    "body" : "<p>I use the Android KeyStore to encrypt the password using RSA in ECB mode and then save it in the SharedPreferences.</p>\n\n<p>When I want the password back I read the encrypted one from the SharedPreferences and decrypt it using the KeyStore.</p>\n\n<p>With this method you generate a public/private Key-pair where the private one is safely stored and managed by Android.</p>\n\n<p>Here is a link on how to do this: <a href=\"https://www.androidauthority.com/use-android-keystore-store-passwords-sensitive-information-623779/\" rel=\"nofollow noreferrer\">Android KeyStore Tutorial</a></p>\n"
  }, {
    "owner" : {
      "account_id" : 6379750,
      "reputation" : 61,
      "user_id" : 4949600,
      "user_type" : "registered",
      "profile_image" : "https://lh4.googleusercontent.com/-6p2U0rZTnJM/AAAAAAAAAAI/AAAAAAAAAG4/UM2qRLh_--I/s256-rj/photo.jpg",
      "display_name" : "becgabi",
      "link" : "https://stackoverflow.com/users/4949600/becgabi"
    },
    "is_accepted" : false,
    "score" : 1,
    "last_activity_date" : 1613626226,
    "creation_date" : 1613626226,
    "answer_id" : 66254186,
    "question_id" : 785973,
    "content_license" : "CC BY-SA 4.0",
    "body" : "<p>As others already pointed out you can use SharedPreferences generally but if you would like to store data encrypted it's a bit inconvenient. Fortunately, there is an easier and quicker way to encrypt data now since there is an implementation of SharedPreferences that encrypts keys and values. You can use <strong>EncryptedSharedPreferences</strong> in Android JetPack Security.</p>\n<p>Just add AndroidX Security into your build.gradle:</p>\n<pre><code>implementation 'androidx.security:security-crypto:1.0.0-rc01'\n</code></pre>\n<p>And you can use it like this:</p>\n<pre><code>String masterKeyAlias = MasterKeys.getOrCreate(MasterKeys.AES256_GCM_SPEC);\n\nSharedPreferences sharedPreferences = EncryptedSharedPreferences.create(\n    &quot;secret_shared_prefs&quot;,\n    masterKeyAlias,\n    context,\n    EncryptedSharedPreferences.PrefKeyEncryptionScheme.AES256_SIV,\n    EncryptedSharedPreferences.PrefValueEncryptionScheme.AES256_GCM\n);\n\n// use the shared preferences and editor as you normally would\nSharedPreferences.Editor editor = sharedPreferences.edit();\n</code></pre>\n<p>See more details: <a href=\"https://android-developers.googleblog.com/2020/02/data-encryption-on-android-with-jetpack.html\" rel=\"nofollow noreferrer\">https://android-developers.googleblog.com/2020/02/data-encryption-on-android-with-jetpack.html</a></p>\n<p>Official docs: <a href=\"https://developer.android.com/reference/androidx/security/crypto/EncryptedSharedPreferences\" rel=\"nofollow noreferrer\">https://developer.android.com/reference/androidx/security/crypto/EncryptedSharedPreferences</a></p>\n"
  }, {
    "owner" : {
      "account_id" : 8491468,
      "reputation" : 1066,
      "user_id" : 8461756,
      "user_type" : "registered",
      "profile_image" : "https://www.gravatar.com/avatar/86db9c1295dfcb1e176f87144ff60f32?s=256&d=identicon&r=PG",
      "display_name" : "Sandeep Dixit",
      "link" : "https://stackoverflow.com/users/8461756/sandeep-dixit"
    },
    "is_accepted" : false,
    "score" : 0,
    "last_activity_date" : 1654961052,
    "last_edit_date" : 1654961052,
    "creation_date" : 1653752260,
    "answer_id" : 72416998,
    "question_id" : 785973,
    "content_license" : "CC BY-SA 4.0",
    "body" : "<p>This is how I am doing it.</p>\n<p>This does not give errors in strict mode.</p>\n<pre><code>public class UserPreferenceUtil\n{\n\n    private static final String  THEME = &quot;THEME&quot;;\n    private static final String  LANGUAGE = &quot;LANGUAGE&quot;;\n\n    public static String getLanguagePreference(Context context)\n    {\n\n        String lang = getPreferenceByKey(context,LANGUAGE);\n\n        if( lang==null || &quot;System&quot;.equalsIgnoreCase(lang))\n        {\n            return null;\n        }\n\n\n        return lang;\n    }\n\n    public static void saveLanguagePreference(Context context,String value)\n    {\n        savePreferenceKeyValue(context, LANGUAGE,value);\n    }\n\n    public static String getThemePreference(Context context)\n    {\n\n        return getPreferenceByKey(context,THEME);\n    }\n\n    public static void saveThemePreference(Context context, String value)\n    {\n        savePreferenceKeyValue(context,THEME,value);\n\n    }\n\n    public static String getPreferenceByKey(Context context, String preferenceKey )\n    {\n        SharedPreferences sharedPreferences = PreferenceManager.getDefaultSharedPreferences(context);\n\n        String value = sharedPreferences.getString(preferenceKey, null);\n\n        return value;\n    }\n\n    private static void savePreferenceKeyValue(Context context, String preferenceKey, String value)\n    {\n        SharedPreferences sharedPreferences = PreferenceManager.getDefaultSharedPreferences(context);\n        SharedPreferences.Editor editor = sharedPreferences.edit();\n        editor.putString(preferenceKey,value);\n        editor.apply();\n\n    }\n\n\n}\n</code></pre>\n<p>My app does not need a password. However, rather than saving passwords or encrypted passwords, I would save a one-way hash. When the user logs in, I will hash the input the same way and match it with the stored hash.</p>\n"
  } ],
  "owner" : {
    "account_id" : 11824,
    "reputation" : 66575,
    "user_id" : 22996,
    "user_type" : "registered",
    "accept_rate" : 92,
    "profile_image" : "https://i.sstatic.net/14C60.jpg?s=256",
    "display_name" : "Niko Gamulin",
    "link" : "https://stackoverflow.com/users/22996/niko-gamulin"
  },
  "is_answered" : true,
  "view_count" : 161338,
  "accepted_answer_id" : 786588,
  "answer_count" : 16,
  "score" : 322,
  "last_activity_date" : 1654961052,
  "creation_date" : 1240581788,
  "last_edit_date" : 1401949530,
  "question_id" : 785973,
  "link" : "https://stackoverflow.com/questions/785973/what-is-the-most-appropriate-way-to-store-user-settings-in-android-application",
  "title" : "What is the most appropriate way to store user settings in Android application",
  "body" : "<p>I am creating an application which connects to the server using username/password and I would like to enable the option \"Save password\" so the user wouldn't have to type the password each time the application starts.</p>\n\n<p>I was trying to do it with Shared Preferences but am not sure if this is the best solution.</p>\n\n<p>I would appreciate any suggestion on how to store user values/settings in Android application.</p>\n"
}